{"MEXC|||Lalo4as|||187.52": {"available": 698.95, "ad_type": "SELL"}, "MEXC|||safe wz me|||187.51": {"available": 3000.0, "ad_type": "SELL"}, "MEXC|||Novatrade|||187.4": {"available": 1000.0, "ad_type": "SELL"}, "MEXC|||y1000guaranee for trader|||187.32": {"available": 624.0, "ad_type": "SELL"}, "MEXC|||Smart Trader|||187.3": {"available": 83.94, "ad_type": "SELL"}, "MEXC|||@Tom|||187.3": {"available": 1572.8778, "ad_type": "SELL"}, "MEXC|||Dlnaod|||187.26": {"available": 535.0, "ad_type": "SELL"}, "MEXC|||Aviator_24/7|||187.0": {"available": 1954.8252, "ad_type": "SELL"}, "MEXC|||Launch-pool Coin \ud83e\ude99|||186.8": {"available": 4030.3425, "ad_type": "SELL"}, "MEXC|||Mann jiii|||186.7": {"available": 1910.2538, "ad_type": "SELL"}, "MEXC|||trust wz me|||186.67": {"available": 900.0, "ad_type": "SELL"}, "MEXC|||Dlnaod|||186.61": {"available": 515.0, "ad_type": "SELL"}, "MEXC|||Waanofii -Crypto|||186.1": {"available": 158.1343, "ad_type": "SELL"}, "MEXC|||Sale_19|||186.09": {"available": 120.0, "ad_type": "SELL"}, "MEXC|||Danival|||186.05": {"available": 1500.0, "ad_type": "SELL"}, "MEXC|||NAWRO  TRADE\u2705|||184.3": {"available": 65672.7257, "ad_type": "SELL"}, "MEXC|||Danival|||184.27": {"available": 1292.618, "ad_type": "SELL"}, "MEXC|||Honest_Man|||184.0": {"available": 300.0, "ad_type": "SELL"}, "MEXC|||GTD_Alsen|||184.0": {"available": 100.0, "ad_type": "SELL"}, "MEXC|||GTD_Alsen|||183.6": {"available": 350.0, "ad_type": "SELL"}}