{"MEXC|||no merchants|||186.5": {"available": 2587.1314, "ad_type": "SELL"}, "MEXC|||Lalo4as|||186.36": {"available": 7210.8823, "ad_type": "SELL"}, "MEXC|||kamnass|||186.3": {"available": 986.334, "ad_type": "SELL"}, "MEXC|||LMJ\ud83d\udfea\ud83d\udd37\ufe0f\ud83d\udfe9fast 3|||186.02": {"available": 1613.0, "ad_type": "SELL"}, "MEXC|||LMJ\ud83d\udfea\ud83d\udd37\ufe0f\ud83d\udfe9fast 3|||186.01": {"available": 340.0, "ad_type": "SELL"}, "MEXC|||kamnass|||186.0": {"available": 322.0, "ad_type": "SELL"}, "MEXC|||we grow 2gzr|||186.0": {"available": 1500.0, "ad_type": "SELL"}, "MEXC|||Noor Capital Flow|||186.0": {"available": 1613.0, "ad_type": "SELL"}, "MEXC|||Billionaire12|||186.0": {"available": 55.0, "ad_type": "SELL"}, "MEXC|||Always_Me|||185.81": {"available": 334.89, "ad_type": "SELL"}, "MEXC|||Melak|||175.0": {"available": 72.5715, "ad_type": "BUY"}, "MEXC|||Danival|||185.0": {"available": 48.0, "ad_type": "BUY"}, "MEXC|||\u2705 Alhamdulillah|||185.9": {"available": 445.0, "ad_type": "BUY"}, "MEXC|||swift_|||186.0": {"available": 749.3494, "ad_type": "BUY"}, "MEXC|||Welcome \ud83e\udd1d|||186.3": {"available": 502.0, "ad_type": "BUY"}, "MEXC|||\u011cg-11|||186.45": {"available": 361.0405, "ad_type": "BUY"}, "MEXC|||Fast trader100%|||186.49": {"available": 843.6, "ad_type": "BUY"}, "MEXC|||Trust Level|||186.89": {"available": 336.0, "ad_type": "BUY"}, "MEXC|||WakandaForever|||187.0": {"available": 200.0, "ad_type": "BUY"}, "MEXC|||shiro-market|||187.08": {"available": 639.1478, "ad_type": "BUY"}}