{"MEXC|||Danival|||183.5": {"available": 42.0, "ad_type": "BUY"}, "MEXC|||Fanos-Crypto|||183.99": {"available": 805.7572, "ad_type": "BUY"}, "MEXC|||MarGioM|||182.8": {"available": 526.7632, "ad_type": "BUY"}, "MEXC|||Fast trader100%|||183.99": {"available": 989.4155, "ad_type": "BUY"}, "MEXC|||new-coin|||184.16": {"available": 77.9784, "ad_type": "BUY"}, "MEXC|||SwiftTrader2018|||184.27": {"available": 850.0, "ad_type": "BUY"}, "MEXC|||All_trade _official|||184.35": {"available": 477.2633, "ad_type": "BUY"}, "MEXC|||\u221a Trusted|||184.37": {"available": 436.471, "ad_type": "BUY"}, "MEXC|||P2P-4848|||184.37": {"available": 75.7904, "ad_type": "BUY"}, "MEXC|||\u011cg-11|||184.55": {"available": 60.49, "ad_type": "BUY"}}