{"MEXC|||Danival|||186.0": {"available": 50.0, "ad_type": "BUY"}, "MEXC|||MarGioM|||184.8": {"available": 93.9242, "ad_type": "BUY"}, "MEXC|||Fanos-Crypto|||185.97": {"available": 366.707, "ad_type": "BUY"}, "MEXC|||Danival|||185.98": {"available": 1291.439, "ad_type": "BUY"}, "MEXC|||crypto345|||186.19": {"available": 104.3329, "ad_type": "BUY"}, "MEXC|||\u221a Trust For All|||186.26": {"available": 418.9042, "ad_type": "BUY"}, "MEXC|||NAWRO  TRADE\u2705|||186.3": {"available": 1101.4415, "ad_type": "BUY"}, "MEXC|||bellon|||186.32": {"available": 133.1245, "ad_type": "BUY"}, "MEXC|||HT2424|||186.32": {"available": 1070.342, "ad_type": "BUY"}, "MEXC|||FAM|||186.35": {"available": 75.0001, "ad_type": "BUY"}, "MEXC|||Abdii|||186.73": {"available": 135.4707, "ad_type": "BUY"}, "MEXC|||y1000guaranee for trader|||186.74": {"available": 404.7, "ad_type": "BUY"}, "MEXC|||MIF.M|||186.78": {"available": 280.4122, "ad_type": "BUY"}, "MEXC|||\u011cg-11|||186.85": {"available": 404.8146, "ad_type": "BUY"}, "MEXC|||The Honest|||186.99": {"available": 373.7859, "ad_type": "BUY"}, "MEXC|||SwiftTrader2018|||186.99": {"available": 400.0725, "ad_type": "BUY"}, "MEXC|||crypto\ud83d\udc80\ud83d\ude0e|||187.0": {"available": 50.1491, "ad_type": "BUY"}, "MEXC|||Lalo4as|||187.29": {"available": 390.8666, "ad_type": "BUY"}, "MEXC|||hka trading|||187.39": {"available": 313.6324, "ad_type": "BUY"}}