{"MEXC|||Danival|||2.0": {"available": 21.0, "ad_type": "BUY"}, "MEXC|||MIF.M|||186.6": {"available": 71.3602, "ad_type": "BUY"}, "MEXC|||\u12e81000|||187.0": {"available": 120.2643, "ad_type": "BUY"}, "MEXC|||Kokeb|||187.11": {"available": 603.4513, "ad_type": "BUY"}, "MEXC|||Trust Pay Now\ud83d\udcaf|||187.2": {"available": 161.3677, "ad_type": "BUY"}, "MEXC|||NAWRO  TRADE\u2705|||187.4": {"available": 556.9103, "ad_type": "BUY"}, "MEXC|||HS2424|||187.42": {"available": 914.5342, "ad_type": "BUY"}, "MEXC|||Common-user-73120975|||187.5": {"available": 1348.4754, "ad_type": "BUY"}, "MEXC|||Danff74|||187.59": {"available": 455.9504, "ad_type": "BUY"}, "MEXC|||yeshi|||187.6": {"available": 225.4, "ad_type": "BUY"}, "MEXC|||mire@2|||187.65": {"available": 1006.0762, "ad_type": "BUY"}, "MEXC|||nurtrade|||187.7": {"available": 44.8366, "ad_type": "BUY"}, "MEXC|||I will well served|||187.9": {"available": 55.2891, "ad_type": "BUY"}, "MEXC|||Lalo4as|||188.74": {"available": 471.1217, "ad_type": "BUY"}, "MEXC|||\u011cg-11|||188.8": {"available": 225.6001, "ad_type": "BUY"}, "MEXC|||Abdii|||188.95": {"available": 873.1511, "ad_type": "BUY"}, "MEXC|||keol|||188.97": {"available": 252.0729, "ad_type": "BUY"}, "MEXC|||mudt|||188.99": {"available": 474.0913, "ad_type": "BUY"}, "MEXC|||Yonathan|||189.9": {"available": 180.1373, "ad_type": "BUY"}, "MEXC|||Ahmedkhan12|||190.0": {"available": 1931.517, "ad_type": "BUY"}, "MEXC|||TrustedCrypto(V2)|||190.75": {"available": 1710.2216, "ad_type": "BUY"}, "MEXC|||Ahmedkhan12|||200.0": {"available": 2914.3888, "ad_type": "BUY"}, "MEXC|||TrustedCrypto(V2)|||200.0": {"available": 206.138, "ad_type": "BUY"}}