{"MEXC|||Melak|||178.0": {"available": 150.0, "ad_type": "BUY"}, "MEXC|||Danival|||183.0": {"available": 48.0, "ad_type": "BUY"}, "MEXC|||MarGioM|||182.4": {"available": 354.9624, "ad_type": "BUY"}, "MEXC|||ezana|||183.4": {"available": 3000.0, "ad_type": "BUY"}, "MEXC|||Safe12-trade|||183.4": {"available": 51.8713, "ad_type": "BUY"}, "MEXC|||Honest75|||183.4": {"available": 60.8287, "ad_type": "BUY"}, "MEXC|||HT2424|||183.42": {"available": 129.1175, "ad_type": "BUY"}, "MEXC|||\u2705 Alhamdulillah|||183.6": {"available": 450.0, "ad_type": "BUY"}, "MEXC|||Fanos-Crypto|||183.68": {"available": 800.4673, "ad_type": "BUY"}, "MEXC|||Fast trader100%|||183.69": {"available": 606.0, "ad_type": "BUY"}}