{"MEXC|||Alpha23-P2P|||189.1": {"available": 140.0, "ad_type": "SELL"}, "MEXC|||trustful|||189.01": {"available": 284.97, "ad_type": "SELL"}, "MEXC|||Melak|||189.0": {"available": 300.0, "ad_type": "SELL"}, "MEXC|||TheSnipe|||189.0": {"available": 4300.0, "ad_type": "SELL"}, "MEXC|||Selassian|||189.0": {"available": 1537.9998, "ad_type": "SELL"}, "MEXC|||SIIFOL|||188.8": {"available": 230.5295, "ad_type": "SELL"}, "MEXC|||D12good|||188.72": {"available": 440.0, "ad_type": "SELL"}, "MEXC|||online|||188.72": {"available": 1300.0, "ad_type": "SELL"}, "MEXC|||love@|||188.72": {"available": 1851.8079, "ad_type": "SELL"}, "MEXC|||Girum|||188.71": {"available": 700.0, "ad_type": "SELL"}}