{"MEXC|||Bahre99|||190.35": {"available": 625.68, "ad_type": "SELL"}, "MEXC|||Mann jiii|||190.13": {"available": 974.0442, "ad_type": "SELL"}, "MEXC|||Joo|||190.13": {"available": 163.6209, "ad_type": "SELL"}, "MEXC|||Trust Level|||190.12": {"available": 205.374, "ad_type": "SELL"}, "MEXC|||\ud83e\ude99ETHCoinTrader\ud83e\ude99|||190.11": {"available": 5003.422, "ad_type": "SELL"}, "MEXC|||reliable xi|||190.01": {"available": 233.5441, "ad_type": "SELL"}, "MEXC|||Billionaire12|||190.0": {"available": 796.0, "ad_type": "SELL"}, "MEXC|||Abdii|||189.9": {"available": 172.7985, "ad_type": "SELL"}, "MEXC|||Dlnaod|||189.89": {"available": 151.5, "ad_type": "SELL"}, "MEXC|||Trust For All|||189.87": {"available": 317.004, "ad_type": "SELL"}}