{"MEXC|||Melak|||184.0": {"available": 456.9844, "ad_type": "BUY"}, "MEXC|||Danival|||185.0": {"available": 48.0, "ad_type": "BUY"}, "MEXC|||MarGioM|||184.0": {"available": 309.3504, "ad_type": "BUY"}, "MEXC|||Common-user-16091674|||186.0": {"available": 1.6145, "ad_type": "BUY"}, "MEXC|||\u011cg-11|||186.4": {"available": 146.745, "ad_type": "BUY"}, "MEXC|||world \ud83c\udf0e pro|||186.44": {"available": 410.023, "ad_type": "BUY"}, "MEXC|||AD97@Helis.|||186.45": {"available": 131.0356, "ad_type": "BUY"}, "MEXC|||Fast trader100%|||186.49": {"available": 441.4337, "ad_type": "BUY"}, "MEXC|||Navaye|||186.5": {"available": 140.2001, "ad_type": "BUY"}, "MEXC|||BILLIONAIRE1|||186.98": {"available": 3000.0001, "ad_type": "BUY"}, "MEXC|||y1000guaranee for trader|||186.99": {"available": 329.9, "ad_type": "BUY"}, "MEXC|||Common-user-43981599|||187.0": {"available": 575.512, "ad_type": "BUY"}, "MEXC|||Sale_19|||187.0": {"available": 108.0, "ad_type": "BUY"}, "MEXC|||AB-Mark|||187.3": {"available": 883.231, "ad_type": "BUY"}, "MEXC|||AD97@Helis.|||187.3": {"available": 401.0356, "ad_type": "BUY"}, "MEXC|||NAWRO  TRADE\u2705|||187.32": {"available": 1087.2852, "ad_type": "BUY"}, "MEXC|||ultrafast|||187.35": {"available": 280.7353, "ad_type": "BUY"}, "MEXC|||keol|||187.39": {"available": 55.0568, "ad_type": "BUY"}, "MEXC|||Common-user-72647842|||187.5": {"available": 54.248, "ad_type": "BUY"}, "MEXC|||NatuD|||187.55": {"available": 641.752, "ad_type": "BUY"}, "MEXC|||Joo|||187.65": {"available": 205.8106, "ad_type": "BUY"}, "MEXC|||crypto345|||187.66": {"available": 81.0911, "ad_type": "BUY"}, "MEXC|||Medina1B|||187.69": {"available": 362.4923, "ad_type": "BUY"}, "MEXC|||mohammed@pay|||187.7": {"available": 300.0, "ad_type": "BUY"}, "MEXC|||ontime|||187.7": {"available": 2423.0938, "ad_type": "BUY"}, "MEXC|||SwiftTrader2018|||187.79": {"available": 77.71791349, "ad_type": "BUY"}, "MEXC|||Trust Pay Now\ud83d\udcaf|||187.8": {"available": 300.0324, "ad_type": "BUY"}, "MEXC|||Novatrade|||187.83": {"available": 126.6457, "ad_type": "BUY"}, "MEXC|||AB live Ex|||187.85": {"available": 544.3028, "ad_type": "BUY"}, "MEXC|||zionsi|||187.98": {"available": 50.0763, "ad_type": "BUY"}, "MEXC|||CNN News|||188.0": {"available": 195.3405, "ad_type": "BUY"}, "MEXC|||JR|||188.0": {"available": 355.5754, "ad_type": "BUY"}, "MEXC|||HT2424|||188.19": {"available": 865.6248, "ad_type": "BUY"}, "MEXC|||Common-user-69088983|||188.47": {"available": 1471.841, "ad_type": "BUY"}, "MEXC|||Bibo|||188.5": {"available": 1218.7673, "ad_type": "BUY"}, "MEXC|||Yonathan|||188.5": {"available": 104.0747, "ad_type": "BUY"}, "MEXC|||Delight$|||188.75": {"available": 700.0, "ad_type": "BUY"}, "MEXC|||MEX|||188.8": {"available": 109.1063, "ad_type": "BUY"}, "MEXC|||MEX|||188.9": {"available": 135.5217, "ad_type": "BUY"}, "MEXC|||mafi|||189.0": {"available": 259.3854, "ad_type": "BUY"}, "MEXC|||Yonathan|||189.74": {"available": 247.0, "ad_type": "BUY"}, "MEXC|||Waanofii -Crypto|||189.86": {"available": 58.0598, "ad_type": "BUY"}, "MEXC|||mire@2|||189.95": {"available": 452.9744, "ad_type": "BUY"}, "MEXC|||TheSnipe|||189.96": {"available": 1360.34, "ad_type": "BUY"}, "MEXC|||Alex\u00a5\u00a9|||190.0": {"available": 145.8019, "ad_type": "BUY"}, "MEXC|||Tol2|||190.47": {"available": 159.9593, "ad_type": "BUY"}, "MEXC|||Luke_Mr|||190.48": {"available": 1600.0, "ad_type": "BUY"}, "MEXC|||Luke_Mr|||190.98": {"available": 1575.0, "ad_type": "BUY"}, "MEXC|||Luke_Mr|||191.98": {"available": 1600.0, "ad_type": "BUY"}}