{"BINANCE|||Feed-Creator-6aff2761f|||184.3": {"available": 80.0, "ad_type": "SELL"}, "BINANCE|||SafeAndTrusted|||184.3": {"available": 8778.53, "ad_type": "SELL"}, "BINANCE|||Janmeda21|||184.3": {"available": 23.0, "ad_type": "SELL"}, "BINANCE|||Autonline|||184.3": {"available": 57973.12, "ad_type": "SELL"}, "BINANCE|||Fast_and_Safe_TR|||184.3": {"available": 48374.47, "ad_type": "SELL"}, "BINANCE|||no-one1|||184.3": {"available": 49491.05, "ad_type": "SELL"}, "BINANCE|||zillion32|||184.3": {"available": 17.94, "ad_type": "SELL"}, "BINANCE|||Changeme21|||184.3": {"available": 98864.22, "ad_type": "SELL"}, "BINANCE|||NegadrasH|||184.3": {"available": 48036.43, "ad_type": "SELL"}, "BINANCE|||B I S M I L L A A H I _ trader _99|||184.3": {"available": 149650.12, "ad_type": "SELL"}, "BINANCE|||Honest-Crypto1|||184.3": {"available": 49900.06, "ad_type": "SELL"}, "BINANCE|||P2P-myTwinsAreComing|||184.3": {"available": 49030.19, "ad_type": "SELL"}, "BINANCE|||Gitsini|||184.3": {"available": 40836.19, "ad_type": "SELL"}, "BINANCE|||Badhaasaatrade|||184.3": {"available": 30000.0, "ad_type": "SELL"}, "BINANCE|||User-e5d6a|||184.26": {"available": 165.0, "ad_type": "SELL"}, "BINANCE|||Regular  P2P|||184.24": {"available": 50000.0, "ad_type": "SELL"}, "BINANCE|||stayy strong |||184.24": {"available": 958166.58, "ad_type": "SELL"}, "BINANCE|||Amana_Traders |||184.23": {"available": 150000.0, "ad_type": "SELL"}, "BINANCE|||asse-go-trade|||184.23": {"available": 50000.0, "ad_type": "SELL"}, "BINANCE|||HIN GAABBU _trader_A|||184.23": {"available": 36054.55, "ad_type": "SELL"}, "BINANCE|||mougadaa|||184.23": {"available": 561.54, "ad_type": "SELL"}, "BINANCE|||Habesha_horizon|||184.23": {"available": 47887.34, "ad_type": "SELL"}, "BINANCE|||Zdntrusted|||184.23": {"available": 149556.63, "ad_type": "SELL"}, "BINANCE|||P2P-725zs1Ilo|||184.23": {"available": 100000.0, "ad_type": "SELL"}, "BINANCE|||Satoshi_Seekerr|||184.23": {"available": 45443.7, "ad_type": "SELL"}, "BINANCE|||ETHO  KENYAA|||184.23": {"available": 60946.13, "ad_type": "SELL"}, "BINANCE|||SafeHold |||184.23": {"available": 49000.1, "ad_type": "SELL"}, "BINANCE|||All_trade_officail|||184.23": {"available": 43631.41, "ad_type": "SELL"}, "BINANCE|||ABCtrading|||184.23": {"available": 50000.0, "ad_type": "SELL"}, "BINANCE|||tiktakh_cry|||184.23": {"available": 29837.17, "ad_type": "SELL"}, "BINANCE|||Hayme_Man|||184.23": {"available": 49706.75, "ad_type": "SELL"}, "BINANCE|||Futsum_SpeedyTrader|||184.23": {"available": 35755.39, "ad_type": "SELL"}, "BINANCE|||FARUK-A|||184.23": {"available": 49973.09, "ad_type": "SELL"}, "BINANCE|||Ambasel |||184.23": {"available": 498996.72, "ad_type": "SELL"}, "BINANCE|||ADUNIX|||184.23": {"available": 50000.0, "ad_type": "SELL"}, "BINANCE|||Aslam72 _72|||184.23": {"available": 49591.17, "ad_type": "SELL"}, "BINANCE|||TRADE-here_PRO|||184.23": {"available": 8217.81, "ad_type": "SELL"}, "BINANCE|||Digital-Diva|||184.23": {"available": 9906.86, "ad_type": "SELL"}, "BINANCE|||MAYA-Bit|||184.23": {"available": 996396.65, "ad_type": "SELL"}, "BINANCE|||Alpha-_-Exchange|||184.23": {"available": 50000.0, "ad_type": "SELL"}, "BINANCE|||ETHIO USD|||184.23": {"available": 1496255.54, "ad_type": "SELL"}, "BINANCE|||Aymi-Fi|||184.23": {"available": 50000.0, "ad_type": "SELL"}, "BINANCE|||abenu-Gg11|||184.23": {"available": 39833.44, "ad_type": "SELL"}, "BINANCE|||B I S M I L L A A H I _ trader _99|||184.23": {"available": 198817.62, "ad_type": "SELL"}, "BINANCE|||Marksolve|||184.23": {"available": 46791.18, "ad_type": "SELL"}, "BINANCE|||HA-12-|||184.23": {"available": 199138.22, "ad_type": "SELL"}, "BINANCE|||EIB_kollubistes|||184.23": {"available": 100.0, "ad_type": "SELL"}, "BINANCE|||M I TRADER |||184.23": {"available": 50000.0, "ad_type": "SELL"}, "BINANCE|||AMIIN_TRADER|||184.23": {"available": 50000.0, "ad_type": "SELL"}, "BINANCE|||Search-more|||184.23": {"available": 49484.77, "ad_type": "SELL"}, "BINANCE|||AD1897-Crypto|||184.23": {"available": 49970.06, "ad_type": "SELL"}, "BINANCE|||All-possible|||184.23": {"available": 48981.03, "ad_type": "SELL"}, "BINANCE|||zorlash|||184.23": {"available": 49949.53, "ad_type": "SELL"}, "BINANCE|||MUST08|||184.23": {"available": 500.0, "ad_type": "SELL"}, "BINANCE||| \u0645\u062d\u0645\u062f \u062c\u0639\u0641\u0631 \u0627\u0644\u0623\u0645\u064a\u0646 |||184.23": {"available": 385.39, "ad_type": "SELL"}, "BINANCE|||OrbitCentral|||184.23": {"available": 19950.06, "ad_type": "SELL"}, "BINANCE|||fastly_Online-1|||184.23": {"available": 500000.0, "ad_type": "SELL"}, "BINANCE|||tiruyee|||184.23": {"available": 1192.18, "ad_type": "SELL"}, "BINANCE|||Brukie21|||184.23": {"available": 19520.35, "ad_type": "SELL"}, "BINANCE|||Tiger149|||184.23": {"available": 308.53, "ad_type": "SELL"}, "BINANCE|||QuickSwap----|||184.23": {"available": 18580.0, "ad_type": "SELL"}, "BINANCE|||choli_choye|||184.23": {"available": 48442.99, "ad_type": "SELL"}, "BINANCE|||SOTTmax|||184.22": {"available": 50000.0, "ad_type": "SELL"}, "BINANCE|||annye1|||184.22": {"available": 454.53, "ad_type": "SELL"}, "BINANCE|||ETHIO USD|||184.22": {"available": 1500000.0, "ad_type": "SELL"}, "BINANCE|||yordi_|||184.22": {"available": 6648.0, "ad_type": "SELL"}, "BINANCE|||Aslam72 _72|||184.22": {"available": 46650.15, "ad_type": "SELL"}, "BINANCE|||ETHIO USD|||184.21": {"available": 1499875.34, "ad_type": "SELL"}, "BINANCE|||P2P-d0dc2d7s|||184.2": {"available": 289.0, "ad_type": "SELL"}, "BINANCE|||Changeme21|||184.2": {"available": 485649.83, "ad_type": "SELL"}, "BINANCE|||Top_Rate_Deals|||184.2": {"available": 45349.1, "ad_type": "SELL"}, "BINANCE|||Super_Ex|||184.2": {"available": 48934.67, "ad_type": "SELL"}, "BINANCE|||M E N H A A J _ 1|||184.2": {"available": 50000.0, "ad_type": "SELL"}, "BINANCE|||Feyisa Ajema|||184.19": {"available": 9640.0, "ad_type": "SELL"}, "BINANCE|||Amar365|||184.19": {"available": 5915.83, "ad_type": "SELL"}, "BINANCE|||Bahre99|||184.19": {"available": 542.1, "ad_type": "SELL"}, "BINANCE|||Autonline|||184.18": {"available": 67309.28, "ad_type": "SELL"}, "BINANCE|||Netbet|||184.0": {"available": 1490663.89, "ad_type": "SELL"}, "BINANCE|||ZataTrade123|||184.0": {"available": 1000.0, "ad_type": "SELL"}, "BINANCE|||TRADE-here_PRO|||184.0": {"available": 15000.0, "ad_type": "SELL"}, "BINANCE|||Alazargasol|||184.0": {"available": 46354.88, "ad_type": "SELL"}, "BINANCE|||EkCryptoExch|||183.5": {"available": 1499985.44, "ad_type": "SELL"}, "BINANCE|||Imran944a|||183.5": {"available": 119136.28, "ad_type": "SELL"}, "BINANCE|||abfaTraders|||183.48": {"available": 396486.43, "ad_type": "SELL"}, "BINANCE|||Luke-Mr|||183.2": {"available": 50000.0, "ad_type": "SELL"}, "BINANCE|||Zdntrusted|||183.2": {"available": 200000.0, "ad_type": "SELL"}, "BINANCE|||abeembwbaz|||183.1": {"available": 49980.06, "ad_type": "SELL"}, "BINANCE|||UrjiiTrade|||183.05": {"available": 50000.0, "ad_type": "SELL"}, "BINANCE|||TRUSTPAYX|||183.03": {"available": 49397.13, "ad_type": "SELL"}, "BINANCE|||siztoz|||183.01": {"available": 50000.0, "ad_type": "SELL"}, "BINANCE|||Dambalash |||183.0": {"available": 49980.0, "ad_type": "SELL"}, "BINANCE|||Nahida N|||183.0": {"available": 48142.06, "ad_type": "SELL"}, "BINANCE|||B I S M I L L A A H I _ trader _99|||183.0": {"available": 499400.06, "ad_type": "SELL"}, "BINANCE|||P2P-725zs1Ilo|||183.0": {"available": 200000.0, "ad_type": "SELL"}, "BINANCE|||destanati|||183.0": {"available": 141.06, "ad_type": "SELL"}, "BINANCE|||mire_02|||183.0": {"available": 48793.31, "ad_type": "SELL"}, "BINANCE|||hanadxirsi|||182.9": {"available": 50000.0, "ad_type": "SELL"}, "BINANCE|||PrimeTrust24|||182.81": {"available": 899621.33, "ad_type": "SELL"}, "BINANCE|||The ultimate goal 1|||182.6": {"available": 1142.89, "ad_type": "SELL"}, "BINANCE|||tintaAm|||182.5": {"available": 1973.12, "ad_type": "SELL"}, "BINANCE|||P2P-1e5653ws|||182.5": {"available": 500.0, "ad_type": "SELL"}, "BINANCE|||McM p7|||182.42": {"available": 497740.56, "ad_type": "SELL"}, "BINANCE|||Harir Meri|||182.4": {"available": 50000.0, "ad_type": "SELL"}, "BINANCE|||Super_trader9|||182.3": {"available": 1996458.0, "ad_type": "SELL"}, "BINANCE|||AlteWay-|||182.26": {"available": 199642.8, "ad_type": "SELL"}, "BINANCE|||_Here_We_Go_|||182.25": {"available": 198903.45, "ad_type": "SELL"}, "BINANCE|||Three million |||182.21": {"available": 50000.0, "ad_type": "SELL"}, "BINANCE|||AK-Infinity |||182.2": {"available": 50000.0, "ad_type": "SELL"}, "BINANCE|||Zdntrusted|||182.2": {"available": 500000.0, "ad_type": "SELL"}, "BINANCE|||Adira-123|||182.11": {"available": 989033.02, "ad_type": "SELL"}, "BINANCE|||\u1e6cheFlash_Trader|||182.11": {"available": 49572.78, "ad_type": "SELL"}, "BINANCE|||Chat_ID_orTG_j0yeeee|||182.02": {"available": 49567.1, "ad_type": "SELL"}, "BINANCE|||Angel190721|||182.01": {"available": 49600.68, "ad_type": "SELL"}, "BINANCE|||GO_UP_GO|||182.0": {"available": 1991691.59, "ad_type": "SELL"}, "BINANCE|||Honest is my identity|||182.0": {"available": 52500.0, "ad_type": "SELL"}, "BINANCE|||Mare_ab|||182.0": {"available": 2901.04, "ad_type": "SELL"}, "BINANCE|||Wogish|||182.0": {"available": 2824.69, "ad_type": "SELL"}, "BINANCE|||P2P 20|||182.0": {"available": 50000.0, "ad_type": "SELL"}, "BINANCE|||Trusted_A|||182.0": {"available": 299700.06, "ad_type": "SELL"}, "BINANCE|||Diamond-ETB|||181.99": {"available": 49902.18, "ad_type": "SELL"}, "BINANCE|||SabbanFastTrader|||181.99": {"available": 499363.22, "ad_type": "SELL"}, "BINANCE|||dodohavq|||181.92": {"available": 19314.58, "ad_type": "SELL"}, "BINANCE|||PrimeTrust24|||181.76": {"available": 1900000.0, "ad_type": "SELL"}, "BINANCE|||agef5q2c|||181.76": {"available": 485.06, "ad_type": "SELL"}, "BINANCE|||Gedilove|||181.69": {"available": 47445.58, "ad_type": "SELL"}, "BINANCE|||the only one p2p |||181.61": {"available": 50000.0, "ad_type": "SELL"}, "BINANCE|||Tawakal-99|||181.5": {"available": 49994.33, "ad_type": "SELL"}, "BINANCE|||GO_UP_GO|||181.5": {"available": 1999915.92, "ad_type": "SELL"}, "BINANCE|||HalalTrader 02|||181.5": {"available": 4989.03, "ad_type": "SELL"}, "BINANCE|||Princess of p2p|||181.5": {"available": 50000.0, "ad_type": "SELL"}, "BINANCE|||welcome back2677|||181.49": {"available": 46200.12, "ad_type": "SELL"}, "BINANCE|||Dagem|||181.48": {"available": 2000000.0, "ad_type": "SELL"}, "BINANCE|||best p2p exchanger|||181.48": {"available": 50000.0, "ad_type": "SELL"}, "BINANCE|||Suldantrader|||181.47": {"available": 50000.0, "ad_type": "SELL"}, "BINANCE|||Baba inaya 17|||181.47": {"available": 50000.0, "ad_type": "SELL"}, "BINANCE|||Halal treading |||181.47": {"available": 50000.0, "ad_type": "SELL"}, "BINANCE|||Ti-Yam|||181.46": {"available": 41024.94, "ad_type": "SELL"}, "BINANCE|||CHEETAH_KALEAB|||181.46": {"available": 50000.0, "ad_type": "SELL"}, "BINANCE|||abee|||181.46": {"available": 14629.2, "ad_type": "SELL"}, "BINANCE|||ETHIO_TRADER_01|||181.45": {"available": 49949.07, "ad_type": "SELL"}, "BINANCE|||MAYA-Bit|||181.43": {"available": 6852.39, "ad_type": "SELL"}, "BINANCE|||HA-12-|||181.31": {"available": 99500.0, "ad_type": "SELL"}, "BINANCE|||Fast and safety payment|||181.3": {"available": 50000.0, "ad_type": "SELL"}, "BINANCE|||BASHASHA BASHASHA77|||181.3": {"available": 50000.0, "ad_type": "SELL"}, "BINANCE|||Reliable for All|||181.3": {"available": 50000.0, "ad_type": "SELL"}, "BINANCE|||Bek-21|||181.29": {"available": 3500.0, "ad_type": "SELL"}, "BINANCE|||sayid12|||181.29": {"available": 49813.72, "ad_type": "SELL"}, "BINANCE|||User-f2522|||181.29": {"available": 49907.15, "ad_type": "SELL"}, "BINANCE|||ETHcryptoETH|||181.28": {"available": 49938.24, "ad_type": "SELL"}, "BINANCE|||The Flash ETB |||181.28": {"available": 143031.65, "ad_type": "SELL"}, "BINANCE|||instant_payee|||181.28": {"available": 49114.74, "ad_type": "SELL"}, "BINANCE|||CryptoFlow_12|||181.28": {"available": 49968.79, "ad_type": "SELL"}, "BINANCE|||zuffy|||181.26": {"available": 30000.0, "ad_type": "SELL"}, "BINANCE|||Bekid10|||181.26": {"available": 275.0, "ad_type": "SELL"}, "BINANCE|||Tomi 13|||181.25": {"available": 1000.0, "ad_type": "SELL"}, "BINANCE|||Peace_For_All|||181.24": {"available": 50000.0, "ad_type": "SELL"}, "BINANCE|||selam_first|||181.23": {"available": 797.25, "ad_type": "SELL"}, "BINANCE|||Shonna Molden n5i5|||181.23": {"available": 50000.0, "ad_type": "SELL"}, "BINANCE|||Geesi|||181.23": {"available": 29984.06, "ad_type": "SELL"}, "BINANCE|||P2P-9a69582b|||181.23": {"available": 20.0, "ad_type": "SELL"}, "BINANCE|||Quick_trader_2025|||181.23": {"available": 598303.34, "ad_type": "SELL"}, "BINANCE|||nakuma|||181.19": {"available": 3740.23, "ad_type": "SELL"}, "BINANCE|||AB USD|||181.19": {"available": 49725.16, "ad_type": "SELL"}, "BINANCE|||Trusted-Exchange9|||181.19": {"available": 49388.65, "ad_type": "SELL"}, "BINANCE|||ceasar_20|||181.19": {"available": 484.42, "ad_type": "SELL"}, "BINANCE|||Philip-Jiao|||181.18": {"available": 1000.0, "ad_type": "SELL"}, "BINANCE|||HD-Hiyaw|||181.18": {"available": 45000.0, "ad_type": "SELL"}, "BINANCE|||kalgold|||181.16": {"available": 2000.0, "ad_type": "SELL"}, "BINANCE|||REAL-CRYPTO-ETB-EXCH|||181.15": {"available": 1500000.0, "ad_type": "SELL"}, "BINANCE|||abduke|||181.12": {"available": 156.0, "ad_type": "SELL"}, "BINANCE|||Masterpos|||181.11": {"available": 750.0, "ad_type": "SELL"}, "BINANCE|||cha27|||181.11": {"available": 475.7, "ad_type": "SELL"}, "BINANCE|||Abe007X|||181.11": {"available": 1000.0, "ad_type": "SELL"}, "BINANCE|||Halal Trading - \u062d\u0644\u0627\u0644 \u0644\u0644\u062a\u062f\u0627\u0648\u0644\u0627\u062a|||181.11": {"available": 50000.0, "ad_type": "SELL"}, "BINANCE|||ETHCoinTrader|||181.11": {"available": 10000.0, "ad_type": "SELL"}, "BINANCE|||Remedan20|||181.11": {"available": 40388.98, "ad_type": "SELL"}, "BINANCE|||Jermayah|||181.11": {"available": 38.68, "ad_type": "SELL"}, "BINANCE|||P2P-100-|||181.11": {"available": 10000.0, "ad_type": "SELL"}, "BINANCE|||P2P-zAbmtku|||181.11": {"available": 50.0, "ad_type": "SELL"}, "BINANCE|||Bisruta|||181.11": {"available": 100.0, "ad_type": "SELL"}, "BINANCE|||EmranZen|||181.11": {"available": 500.06, "ad_type": "SELL"}, "BINANCE|||Aba-Mela|||181.11": {"available": 200.0, "ad_type": "SELL"}, "BINANCE|||Reza-Milka|||181.11": {"available": 987.31, "ad_type": "SELL"}, "BINANCE|||-Zenith-|||181.11": {"available": 5753.18, "ad_type": "SELL"}, "BINANCE|||Medu12|||181.11": {"available": 1000.0, "ad_type": "SELL"}, "BINANCE|||Y-Leo_16|||181.11": {"available": 49962.36, "ad_type": "SELL"}, "BINANCE|||mike man|||181.11": {"available": 166.0, "ad_type": "SELL"}, "BINANCE|||P2P-81e011bk|||181.11": {"available": 52.0, "ad_type": "SELL"}, "BINANCE|||User-dd199|||181.1": {"available": 1500.0, "ad_type": "SELL"}, "BINANCE|||Tk Familly |||181.06": {"available": 276.15, "ad_type": "SELL"}, "BINANCE|||Ams683|||181.06": {"available": 166.0, "ad_type": "SELL"}, "BINANCE|||YONABESHA|||181.06": {"available": 600.0, "ad_type": "SELL"}, "BINANCE|||Bright_Color|||181.06": {"available": 180.0, "ad_type": "SELL"}, "BINANCE|||wolf1325|||181.04": {"available": 1972.37, "ad_type": "SELL"}, "BINANCE|||real_cryptoo|||181.01": {"available": 50000.0, "ad_type": "SELL"}, "BINANCE|||Safe_Exchange_19|||181.0": {"available": 46743.98, "ad_type": "SELL"}, "BINANCE|||AbukiAh|||181.0": {"available": 828.7, "ad_type": "SELL"}, "BINANCE|||P2P-725zs1Ilo|||181.0": {"available": 300000.0, "ad_type": "SELL"}, "BINANCE|||ETHIOPIA_DOLLAR|||181.0": {"available": 50000.0, "ad_type": "SELL"}, "BINANCE|||Speedyguyy|||180.99": {"available": 50000.0, "ad_type": "SELL"}, "BINANCE|||SabbanFastTrader|||180.99": {"available": 388377.39, "ad_type": "SELL"}, "BINANCE|||McM p7|||180.99": {"available": 283752.1, "ad_type": "SELL"}, "BINANCE|||binaex|||180.96": {"available": 100.0, "ad_type": "SELL"}, "BINANCE|||mercato24|||180.95": {"available": 44220.45, "ad_type": "SELL"}, "BINANCE|||P2P-yaruYa|||180.95": {"available": 138.0, "ad_type": "SELL"}, "BINANCE|||P2P-4e5d88kn|||180.9": {"available": 820.0, "ad_type": "SELL"}, "BINANCE|||AmEthan7 |||180.9": {"available": 1000.0, "ad_type": "SELL"}, "BINANCE|||User-adbf6|||180.85": {"available": 1750.0, "ad_type": "SELL"}, "BINANCE|||smart trader 161616|||180.85": {"available": 15.48, "ad_type": "SELL"}, "BINANCE|||Ethio1888|||180.84": {"available": 10.0, "ad_type": "SELL"}, "BINANCE|||Official_Binances-|||180.83": {"available": 1956.47, "ad_type": "SELL"}, "BINANCE|||P2P-0c547e1g|||180.83": {"available": 5000.0, "ad_type": "SELL"}, "BINANCE|||Dlnaod |||180.83": {"available": 56.0, "ad_type": "SELL"}, "BINANCE|||Rovo4323|||180.82": {"available": 1420.06, "ad_type": "SELL"}, "BINANCE|||Wd-Sami|||180.82": {"available": 10000.0, "ad_type": "SELL"}, "BINANCE|||User-68137|||180.82": {"available": 40.0, "ad_type": "SELL"}, "BINANCE|||mishu--papa|||180.82": {"available": 165.0, "ad_type": "SELL"}, "BINANCE|||DIINAAOL3|||180.82": {"available": 300000.0, "ad_type": "SELL"}, "BINANCE|||pain2|||180.82": {"available": 9970.77, "ad_type": "SELL"}, "BINANCE|||Donum6153|||180.82": {"available": 1000.0, "ad_type": "SELL"}, "BINANCE|||abee|||180.82": {"available": 4970.06, "ad_type": "SELL"}, "BINANCE|||Dagem|||180.82": {"available": 99411.87, "ad_type": "SELL"}, "BINANCE|||Super_trader9|||180.82": {"available": 1991780.45, "ad_type": "SELL"}, "BINANCE|||P2P-b539b9w0|||180.82": {"available": 504.95, "ad_type": "SELL"}, "BINANCE|||User-756b4|||180.81": {"available": 10000.0, "ad_type": "SELL"}, "BINANCE|||Aslam72 _72|||180.81": {"available": 49592.59, "ad_type": "SELL"}, "BINANCE|||Jobirg|||180.8": {"available": 29836.7, "ad_type": "SELL"}, "BINANCE|||Bushretrading|||180.79": {"available": 1580.0, "ad_type": "SELL"}, "BINANCE|||Ori_sha|||180.79": {"available": 400.0, "ad_type": "SELL"}, "BINANCE|||User-6fb83|||180.79": {"available": 400.0, "ad_type": "SELL"}, "BINANCE|||P2P-9129e4so|||180.79": {"available": 1000.0, "ad_type": "SELL"}, "BINANCE|||User-4d90c|||180.79": {"available": 166.0, "ad_type": "SELL"}, "BINANCE|||Afdel22|||180.78": {"available": 10000.0, "ad_type": "SELL"}, "BINANCE|||P2P-075f7ffe|||180.78": {"available": 100.0, "ad_type": "SELL"}, "BINANCE|||Last chance|||180.78": {"available": 50000.0, "ad_type": "SELL"}, "BINANCE|||User-0c5ad|||180.76": {"available": 50.0, "ad_type": "SELL"}, "BINANCE|||JRS-77|||180.76": {"available": 100.0, "ad_type": "SELL"}, "BINANCE|||leaderofcrpoto|||180.76": {"available": 200.0, "ad_type": "SELL"}, "BINANCE|||NP_NHATTY|||180.76": {"available": 1500.0, "ad_type": "SELL"}, "BINANCE|||Neba2321|||180.71": {"available": 25.0, "ad_type": "SELL"}, "BINANCE|||Ibsae|||180.66": {"available": 10.0, "ad_type": "SELL"}, "BINANCE|||P2P-1078c0y4|||180.64": {"available": 885.0, "ad_type": "SELL"}, "BINANCE|||rasyafet2013|||180.64": {"available": 4842.06, "ad_type": "SELL"}, "BINANCE|||king_ETcrypto|||180.64": {"available": 10.0, "ad_type": "SELL"}, "BINANCE|||P2P-b5c41cos|||180.64": {"available": 601.24, "ad_type": "SELL"}, "BINANCE|||User-d3ce9|||180.6": {"available": 500.0, "ad_type": "SELL"}, "BINANCE|||User-647f0|||180.6": {"available": 10.0, "ad_type": "SELL"}, "BINANCE|||Fast-trader_12|||180.57": {"available": 231.24, "ad_type": "SELL"}, "BINANCE|||Harbor_media_network|||180.53": {"available": 150.0, "ad_type": "SELL"}, "BINANCE|||User-d0185|||180.51": {"available": 200.06, "ad_type": "SELL"}, "BINANCE|||ShuaybHassen|||180.4": {"available": 50.06, "ad_type": "SELL"}, "BINANCE|||AURAFX|||180.34": {"available": 11.0, "ad_type": "SELL"}, "BINANCE|||AB-Mark|||180.31": {"available": 36314.02, "ad_type": "SELL"}, "BINANCE|||Dinkin|||180.3": {"available": 46512.3, "ad_type": "SELL"}, "BINANCE|||SKY-blue77|||180.3": {"available": 999582.56, "ad_type": "SELL"}, "BINANCE|||Zhaily_27|||180.25": {"available": 30.0, "ad_type": "SELL"}, "BINANCE|||Melak17|||180.2": {"available": 1000.0, "ad_type": "SELL"}, "BINANCE|||Dadimos1975|||180.2": {"available": 33.06, "ad_type": "SELL"}, "BINANCE|||Lyda Saltourides KIRm|||180.2": {"available": 2583.86, "ad_type": "SELL"}, "BINANCE|||Tewodros Alemu|||180.15": {"available": 8500.0, "ad_type": "SELL"}, "BINANCE|||The Flash ETB |||180.13": {"available": 205000.0, "ad_type": "SELL"}, "BINANCE|||Gizaw M|||180.06": {"available": 222.0, "ad_type": "SELL"}, "BINANCE|||Real_Trdr|||180.05": {"available": 31.0, "ad_type": "SELL"}, "BINANCE|||Zaw12|||180.04": {"available": 87.23, "ad_type": "SELL"}, "BINANCE|||Crypto_Loving|||180.01": {"available": 15036.73, "ad_type": "SELL"}, "BINANCE|||User-gameeee|||180.01": {"available": 50000.0, "ad_type": "SELL"}, "BINANCE|||Firaol Befikadu|||180.01": {"available": 500.0, "ad_type": "SELL"}, "BINANCE|||cryptofaaam|||180.01": {"available": 2100.06, "ad_type": "SELL"}, "BINANCE|||Iaspiretobeagoodmann|||180.0": {"available": 250.0, "ad_type": "SELL"}, "BINANCE|||KakuuShalomtrader|||180.0": {"available": 100.0, "ad_type": "SELL"}, "BINANCE|||emily13addise|||180.0": {"available": 10.0, "ad_type": "SELL"}, "BINANCE|||User-b1041|||180.0": {"available": 150.0, "ad_type": "SELL"}, "BINANCE|||varonlline|||180.0": {"available": 13.0, "ad_type": "SELL"}, "BINANCE|||market_masterio|||180.0": {"available": 7745.98, "ad_type": "SELL"}, "BINANCE|||yeteshale|||180.0": {"available": 100.0, "ad_type": "SELL"}, "BINANCE|||Habesh_t|||180.0": {"available": 2912.12, "ad_type": "SELL"}, "BINANCE|||Sierra Demaree r0Oh|||180.0": {"available": 150.13, "ad_type": "SELL"}, "BINANCE|||Chento21|||180.0": {"available": 8823.0, "ad_type": "SELL"}, "BINANCE|||SabbanFastTrader|||179.99": {"available": 499530.47, "ad_type": "SELL"}, "BINANCE|||BARKI__|||179.0": {"available": 500.0, "ad_type": "SELL"}, "BINANCE|||Mi25|||178.71": {"available": 30.0, "ad_type": "SELL"}, "BINANCE|||User-black lion|||178.0": {"available": 38.47, "ad_type": "SELL"}, "BINANCE|||kemal11|||177.0": {"available": 450.0, "ad_type": "SELL"}, "BINANCE|||zrata|||176.28": {"available": 39880.05, "ad_type": "SELL"}, "BINANCE|||Clear_Gate|||176.28": {"available": 50000.0, "ad_type": "SELL"}, "BINANCE|||YyyyyyyyuyFast|||176.28": {"available": 49974.77, "ad_type": "SELL"}, "BINANCE|||Sol780|||176.27": {"available": 500.0, "ad_type": "SELL"}, "BINANCE|||Adira-123|||176.11": {"available": 995504.25, "ad_type": "SELL"}, "BINANCE|||P2P-3a672ewo|||176.1": {"available": 897.05, "ad_type": "SELL"}, "BINANCE|||Florrie Kundanani oGPy|||176.0": {"available": 100.0, "ad_type": "SELL"}, "BINANCE|||Ami_ka|||175.92": {"available": 14200.0, "ad_type": "SELL"}, "BINANCE|||Crypto-King21|||175.92": {"available": 50000.0, "ad_type": "SELL"}, "BINANCE|||alpha_trade7|||175.9": {"available": 35.0, "ad_type": "SELL"}, "BINANCE|||Biruk77|||175.87": {"available": 35.0, "ad_type": "SELL"}, "BINANCE|||Etial|||175.86": {"available": 200.0, "ad_type": "SELL"}, "BINANCE|||stayy strong |||175.75": {"available": 500000.0, "ad_type": "SELL"}, "BINANCE|||Fikruye|||175.64": {"available": 1000.0, "ad_type": "SELL"}, "BINANCE|||P2P-2bc4a8cm|||175.61": {"available": 10.0, "ad_type": "SELL"}, "BINANCE|||ElsayTrade|||175.52": {"available": 10000.0, "ad_type": "SELL"}, "BINANCE|||FastSafeDeal|||175.41": {"available": 2000.0, "ad_type": "SELL"}, "BINANCE|||ethiotezer|||175.34": {"available": 2100.0, "ad_type": "SELL"}, "BINANCE|||tradingfirm|||175.25": {"available": 44.3, "ad_type": "SELL"}, "BINANCE||||||175.23": {"available": 6029.78, "ad_type": "SELL"}, "BINANCE|||P2P-706a23ma|||175.23": {"available": 97.17, "ad_type": "SELL"}, "BINANCE|||Stellar_one|||175.23": {"available": 200.0, "ad_type": "SELL"}, "BINANCE|||ATR8400|||175.23": {"available": 4500.0, "ad_type": "SELL"}, "BINANCE|||Samson99|||175.22": {"available": 1000.0, "ad_type": "SELL"}, "BINANCE|||Melos2112|||175.17": {"available": 210.0, "ad_type": "SELL"}, "BINANCE|||MNMtrading|||175.1": {"available": 800.18, "ad_type": "SELL"}, "BINANCE|||P2P-9301acey|||175.0": {"available": 100.0, "ad_type": "SELL"}, "BINANCE|||Netbet|||175.0": {"available": 998884.18, "ad_type": "SELL"}, "BINANCE|||thetrustworth|||175.0": {"available": 500.06, "ad_type": "SELL"}, "BINANCE|||P2P-7600ec4i|||174.9": {"available": 100.0, "ad_type": "SELL"}, "BINANCE|||whymelord|||174.9": {"available": 850.0, "ad_type": "SELL"}, "BINANCE|||Gutw|||174.87": {"available": 31.0, "ad_type": "SELL"}, "BINANCE|||P2P-IMichele|||174.83": {"available": 300.0, "ad_type": "SELL"}, "BINANCE|||real_abdu|||174.51": {"available": 8970.94, "ad_type": "SELL"}, "BINANCE|||P2P-057035gs|||174.28": {"available": 20000.0, "ad_type": "SELL"}, "BINANCE|||sisay5|||174.26": {"available": 150.0, "ad_type": "SELL"}, "BINANCE|||SEMREAB|||174.24": {"available": 100.0, "ad_type": "SELL"}, "BINANCE|||engamka|||174.05": {"available": 5000.0, "ad_type": "SELL"}, "BINANCE|||Account For sale |||174.05": {"available": 50000.0, "ad_type": "SELL"}, "BINANCE|||ETBHighborn|||174.05": {"available": 1500.0, "ad_type": "SELL"}, "BINANCE|||E-Sarif|||174.0": {"available": 1000.0, "ad_type": "SELL"}, "BINANCE|||P2P-ba864b6y|||174.0": {"available": 60.0, "ad_type": "SELL"}, "BINANCE|||ETB_Gebeya|||173.86": {"available": 196.47, "ad_type": "SELL"}, "BINANCE|||AbuAmiin|||173.86": {"available": 5000.0, "ad_type": "SELL"}, "BINANCE|||SafeHold |||173.64": {"available": 47850.15, "ad_type": "SELL"}, "BINANCE|||--YG--|||173.56": {"available": 290.0, "ad_type": "SELL"}, "BINANCE|||adatgn|||173.55": {"available": 10000.0, "ad_type": "SELL"}, "BINANCE|||ZuriEt|||173.5": {"available": 1000.0, "ad_type": "SELL"}, "BINANCE|||William4185|||173.47": {"available": 670.0, "ad_type": "SELL"}, "BINANCE|||User-eb1e7|||173.47": {"available": 3.45, "ad_type": "SELL"}, "BINANCE|||Beha16|||173.47": {"available": 120.0, "ad_type": "SELL"}, "BINANCE|||welcome_9|||173.45": {"available": 22.11, "ad_type": "SELL"}, "BINANCE|||ayanmhmd1|||173.43": {"available": 50000.0, "ad_type": "SELL"}, "BINANCE|||P2P-85ffd5vs|||173.36": {"available": 165.0, "ad_type": "SELL"}, "BINANCE|||Sef-Trade|||173.3": {"available": 200.0, "ad_type": "SELL"}, "BINANCE|||Claris Chung KxBE|||173.29": {"available": 50.0, "ad_type": "SELL"}, "BINANCE|||_Abyssinica|||173.28": {"available": 2000.0, "ad_type": "SELL"}, "BINANCE|||P2P-4bea9cld|||173.27": {"available": 856.0, "ad_type": "SELL"}, "BINANCE|||P2P-aa9806wb|||173.26": {"available": 300.0, "ad_type": "SELL"}, "BINANCE|||P2P-0b9e59fz|||173.24": {"available": 1500.0, "ad_type": "SELL"}, "BINANCE|||User-722fe|||173.24": {"available": 10000.0, "ad_type": "SELL"}, "BINANCE|||Dr-Dave|||173.18": {"available": 580.0, "ad_type": "SELL"}, "BINANCE|||the-market_killer|||173.13": {"available": 100.0, "ad_type": "SELL"}, "BINANCE|||Ethio_Best_Trader|||173.11": {"available": 500.0, "ad_type": "SELL"}, "BINANCE||| \u062c\u0628\u0631\u064a\u0644 \u062d\u0633\u064a\u0646  \u0644\u0627 \u062a\u062e\u062f\u0639\u0648\u0646\u064a  \u0625\u062a\u0642\u0648 \u0627\u0644\u0644\u0647 |||173.1": {"available": 200.0, "ad_type": "SELL"}, "BINANCE|||Qubee-Crypto|||173.1": {"available": 259.0, "ad_type": "SELL"}, "BINANCE|||P2P-5dc8957x|||173.1": {"available": 2000.0, "ad_type": "SELL"}, "BINANCE|||Crypto Arada|||173.1": {"available": 1010.0, "ad_type": "SELL"}, "BINANCE|||atotrade|||173.1": {"available": 45.9, "ad_type": "SELL"}, "BINANCE|||dagiman12|||173.02": {"available": 200.0, "ad_type": "SELL"}, "BINANCE|||P2P-2cef98xw|||173.0": {"available": 100.0, "ad_type": "SELL"}, "BINANCE|||maya2222222|||173.0": {"available": 500.0, "ad_type": "SELL"}, "BINANCE|||Mcrypto trader|||173.0": {"available": 11.0, "ad_type": "SELL"}, "BINANCE|||pada4X|||173.0": {"available": 57.8, "ad_type": "SELL"}, "BINANCE|||Ghost4uu|||173.0": {"available": 20.0, "ad_type": "SELL"}, "BINANCE|||AymanGT|||172.82": {"available": 80.05, "ad_type": "SELL"}, "BINANCE|||AltCoinEthiopia|||172.77": {"available": 26.0, "ad_type": "SELL"}, "BINANCE|||P2P-427142pk|||172.76": {"available": 1000.0, "ad_type": "SELL"}, "BINANCE|||NilHem|||172.68": {"available": 10.0, "ad_type": "SELL"}, "BINANCE|||Trustful -Trader |||172.56": {"available": 20.0, "ad_type": "SELL"}, "BINANCE|||ions77|||172.55": {"available": 4638.78, "ad_type": "SELL"}, "BINANCE|||User-f5c32|||172.38": {"available": 73.52, "ad_type": "SELL"}, "BINANCE|||P2P-f37724od|||172.3": {"available": 10.0, "ad_type": "SELL"}, "BINANCE|||PrimeTrust24|||172.23": {"available": 799450.06, "ad_type": "SELL"}, "BINANCE|||Market_is_free|||172.21": {"available": 1500.0, "ad_type": "SELL"}, "BINANCE|||User-543bf|||172.21": {"available": 464.55, "ad_type": "SELL"}, "BINANCE|||P2P-f5bad6qe|||172.17": {"available": 30.0, "ad_type": "SELL"}, "BINANCE|||_Abyssinica|||172.15": {"available": 2450.0, "ad_type": "SELL"}, "BINANCE|||Ezedin_boss12|||172.14": {"available": 10.0, "ad_type": "SELL"}, "BINANCE|||P2P-92f939vn|||172.14": {"available": 4.73, "ad_type": "SELL"}, "BINANCE|||User-e2c66|||172.14": {"available": 100.0, "ad_type": "SELL"}, "BINANCE|||P2P-0356edwf|||172.14": {"available": 20.0, "ad_type": "SELL"}, "BINANCE|||P2P-cf62c0ae|||172.14": {"available": 40.0, "ad_type": "SELL"}, "BINANCE|||nahomalex|||172.0": {"available": 21.0, "ad_type": "SELL"}, "BINANCE|||User-24d4a|||172.0": {"available": 60.0, "ad_type": "SELL"}, "BINANCE|||Tokkumma|||172.0": {"available": 17347.52, "ad_type": "SELL"}, "BINANCE|||amanamduka|||171.39": {"available": 100.0, "ad_type": "SELL"}, "BINANCE|||milkiiii|||170.92": {"available": 100.0, "ad_type": "SELL"}, "BINANCE|||mariibo|||170.88": {"available": 10000.0, "ad_type": "SELL"}, "BINANCE|||Fast_22_LOVE|||170.69": {"available": 100.0, "ad_type": "SELL"}, "BINANCE|||Adi_Trader21|||170.68": {"available": 15.0, "ad_type": "SELL"}, "BINANCE|||Gize27|||170.66": {"available": 15.98, "ad_type": "SELL"}, "BINANCE|||User-72c03|||170.66": {"available": 10.0, "ad_type": "SELL"}, "BINANCE|||Glorius_life|||170.66": {"available": 350.0, "ad_type": "SELL"}, "BINANCE|||DagiHappy2024|||170.65": {"available": 702.05, "ad_type": "SELL"}, "BINANCE|||bondhub|||170.0": {"available": 20.0, "ad_type": "SELL"}, "BINANCE|||Tariku Tesfay|||170.0": {"available": 230.0, "ad_type": "SELL"}, "BINANCE|||User-69ae5|||170.0": {"available": 50.0, "ad_type": "SELL"}, "BINANCE|||Germanax139|||170.0": {"available": 100.0, "ad_type": "SELL"}, "BINANCE|||User-67ac0|||169.87": {"available": 340.0, "ad_type": "SELL"}, "BINANCE|||knight2493|||169.87": {"available": 295.0, "ad_type": "SELL"}, "BINANCE|||Yeabsira|||169.86": {"available": 1000.0, "ad_type": "SELL"}, "BINANCE|||P2P-69e388nk|||169.86": {"available": 10.0, "ad_type": "SELL"}, "BINANCE|||P2P-b3806fkk|||169.86": {"available": 25.0, "ad_type": "SELL"}, "BINANCE|||P2P-7ef20bhv|||169.82": {"available": 120.0, "ad_type": "SELL"}, "BINANCE|||User-369af|||169.77": {"available": 619.69, "ad_type": "SELL"}, "BINANCE|||Chat_ID_orTG_j0yeeee|||155.25": {"available": 10.0, "ad_type": "BUY"}, "BINANCE|||Eye-Trader|||155.36": {"available": 100.0, "ad_type": "BUY"}, "BINANCE|||abfaTraders|||155.41": {"available": 100.0, "ad_type": "BUY"}, "MEXC|||Danival|||2.0": {"available": 44.0, "ad_type": "BUY"}, "MEXC|||@ishow speed|||185.4": {"available": 347.0379, "ad_type": "BUY"}, "MEXC|||Autonline|||185.45": {"available": 260.4773, "ad_type": "BUY"}, "MEXC|||sudina|||185.5": {"available": 282.8946, "ad_type": "BUY"}, "MEXC|||Ambasel|||185.5": {"available": 664.3673, "ad_type": "BUY"}, "MEXC|||pro.|||185.6": {"available": 995.378, "ad_type": "BUY"}, "MEXC|||East-west|||185.67": {"available": 75.0, "ad_type": "BUY"}, "MEXC|||user-H2a1\u2705|||185.77": {"available": 83.1729, "ad_type": "BUY"}, "MEXC|||FanToshi Exchange \ud83d\udcb1|||185.78": {"available": 754.8847, "ad_type": "BUY"}, "MEXC|||AK-Infinity|||185.8": {"available": 409.0305, "ad_type": "BUY"}, "MEXC|||Common-user-73120975|||186.2": {"available": 788.5653, "ad_type": "BUY"}, "MEXC|||runnertra|||186.2": {"available": 104.7685, "ad_type": "BUY"}, "MEXC|||Alhamdulillah\u221a|||186.37": {"available": 293.73, "ad_type": "BUY"}, "MEXC|||ADUNIX|||186.39": {"available": 434.007, "ad_type": "BUY"}, "MEXC|||BadhaasaaTrader|||186.4": {"available": 79.1178, "ad_type": "BUY"}, "MEXC|||Navaye|||186.4": {"available": 168.2859, "ad_type": "BUY"}, "MEXC|||NatuD|||186.4": {"available": 411.0782, "ad_type": "BUY"}, "MEXC|||\u12e81000|||186.45": {"available": 120.0213, "ad_type": "BUY"}, "MEXC|||Winner \ud83c\udfc6|||186.46": {"available": 1082.3956, "ad_type": "BUY"}, "MEXC|||Danival|||186.47": {"available": 897.7159, "ad_type": "BUY"}, "MEXC|||REAL MONEY|||186.48": {"available": 723.8079, "ad_type": "BUY"}, "MEXC|||reliable xi|||186.49": {"available": 118.3574, "ad_type": "BUY"}, "MEXC|||Lalo4as|||186.49": {"available": 247.3782, "ad_type": "BUY"}, "MEXC|||theFlash_trader|||186.5": {"available": 55.6726, "ad_type": "BUY"}, "MEXC|||Shalom-TraderET|||186.65": {"available": 24.2786, "ad_type": "BUY"}, "MEXC|||Common-Trader|||186.69": {"available": 57.9993, "ad_type": "BUY"}, "MEXC|||real business100%|||186.69": {"available": 108.2101, "ad_type": "BUY"}, "MEXC|||safe wz me|||186.69": {"available": 728.3816, "ad_type": "BUY"}, "MEXC|||abdu1B|||186.79": {"available": 134.133, "ad_type": "BUY"}, "MEXC|||Bahre99|||186.85": {"available": 537.6895, "ad_type": "BUY"}, "MEXC|||Qimem|||186.85": {"available": 306.435, "ad_type": "BUY"}, "MEXC|||Billionaire12|||186.88": {"available": 760.9206, "ad_type": "BUY"}, "MEXC|||pro.|||186.9": {"available": 1465.887, "ad_type": "BUY"}, "MEXC|||Time_Based|||186.9": {"available": 281.534, "ad_type": "BUY"}, "MEXC|||ontime|||186.92": {"available": 1262.0363, "ad_type": "BUY"}, "MEXC|||runnertra|||186.95": {"available": 87.0793, "ad_type": "BUY"}, "MEXC|||\u011cg-11|||186.99": {"available": 53.556, "ad_type": "BUY"}, "MEXC|||Rasg-trusted\ud83e\udd47|||186.99": {"available": 539.9472, "ad_type": "BUY"}, "MEXC|||The donate|||187.0": {"available": 274.2241, "ad_type": "BUY"}, "MEXC|||Rasg-trusted\ud83e\udd47|||187.0": {"available": 200.7882, "ad_type": "BUY"}, "MEXC|||Brukie21|||187.0": {"available": 1284.9364, "ad_type": "BUY"}, "MEXC|||Anab Anwar|||187.2": {"available": 325.2137, "ad_type": "BUY"}, "MEXC|||QuantumLeap\ud83d\udc8e|||187.21": {"available": 96.0735, "ad_type": "BUY"}, "MEXC|||nurtrade|||187.3": {"available": 38.7002, "ad_type": "BUY"}, "MEXC|||mudt|||187.39": {"available": 256.6448, "ad_type": "BUY"}, "MEXC|||Investfarm|||187.4": {"available": 579.8074, "ad_type": "BUY"}, "MEXC|||Halal Trader|||187.5": {"available": 57.955, "ad_type": "BUY"}, "MEXC|||digil21|||187.7": {"available": 100.3591, "ad_type": "BUY"}, "MEXC|||keol|||187.89": {"available": 527.5321, "ad_type": "BUY"}, "MEXC|||trusted merchant|||188.0": {"available": 1215.8624, "ad_type": "BUY"}}