{"BINANCE|||Reliable for All|||181.3": {"available": 6881.61, "ad_type": "SELL"}, "BINANCE|||Swap_X|||181.3": {"available": 41888.92, "ad_type": "SELL"}, "BINANCE|||Eliana_Exc|||181.3": {"available": 40666.9, "ad_type": "SELL"}, "BINANCE|||BASHASHA BASHASHA|||181.3": {"available": 44521.18, "ad_type": "SELL"}, "BINANCE|||SabbanFastTrader|||181.3": {"available": 456672.37, "ad_type": "SELL"}, "BINANCE|||Aphteen47|||181.3": {"available": 46986.28, "ad_type": "SELL"}, "BINANCE|||P2P-725zs1Ilo|||181.3": {"available": 84131.58, "ad_type": "SELL"}, "BINANCE|||real huslter|||181.3": {"available": 975341.25, "ad_type": "SELL"}, "BINANCE|||Safe_Exchange_19|||181.3": {"available": 49115.94, "ad_type": "SELL"}, "BINANCE|||kemal abdu yasin |||181.3": {"available": 30395.48, "ad_type": "SELL"}, "BINANCE|||Gitsini|||181.3": {"available": 22495.91, "ad_type": "SELL"}, "BINANCE|||Harir Meri|||181.3": {"available": 43317.32, "ad_type": "SELL"}, "BINANCE|||Honest-Crypto1|||181.3": {"available": 46190.49, "ad_type": "SELL"}, "BINANCE|||HA--Exchange|||181.3": {"available": 48969.41, "ad_type": "SELL"}, "BINANCE|||The ultimate goal 1|||181.3": {"available": 48304.51, "ad_type": "SELL"}, "BINANCE|||Ella water|||181.3": {"available": 282.2, "ad_type": "SELL"}, "BINANCE|||Fast and safety payment|||181.29": {"available": 47836.11, "ad_type": "SELL"}, "BINANCE|||Diamond-ETB|||181.29": {"available": 45946.6, "ad_type": "SELL"}, "BINANCE|||BASHASHA BASHASHA77|||181.29": {"available": 50000.0, "ad_type": "SELL"}, "BINANCE|||Habesha p2p zone |||181.29": {"available": 50000.0, "ad_type": "SELL"}, "BINANCE|||the only one p2p |||181.29": {"available": 50000.0, "ad_type": "SELL"}, "BINANCE|||welcome back2677|||181.29": {"available": 49749.19, "ad_type": "SELL"}, "BINANCE|||no-one1|||181.29": {"available": 47438.58, "ad_type": "SELL"}, "BINANCE|||REAL-MONEY|||181.29": {"available": 998277.25, "ad_type": "SELL"}, "BINANCE|||abeembwbaz|||181.29": {"available": 49294.04, "ad_type": "SELL"}, "BINANCE|||_Here_We_Go_|||181.29": {"available": 151005.4, "ad_type": "SELL"}, "BINANCE|||Ti-Yam|||181.29": {"available": 47656.39, "ad_type": "SELL"}, "BINANCE|||All_trade_officail|||181.29": {"available": 47672.63, "ad_type": "SELL"}, "BINANCE|||B I S M I L L A A H I _ trader _99|||181.29": {"available": 36683.32, "ad_type": "SELL"}, "BINANCE|||Hayme_Man|||181.29": {"available": 4602.87, "ad_type": "SELL"}, "BINANCE|||Changeme21|||181.29": {"available": 495756.84, "ad_type": "SELL"}, "BINANCE|||FanToshi EXchange|||181.29": {"available": 888359.35, "ad_type": "SELL"}, "BINANCE|||AB-Mark|||181.29": {"available": 155695.41, "ad_type": "SELL"}, "BINANCE|||TawekalTrade|||181.29": {"available": 50000.0, "ad_type": "SELL"}, "BINANCE|||dodohavq|||181.29": {"available": 4418.31, "ad_type": "SELL"}, "BINANCE|||real_cryptoo|||181.29": {"available": 45465.43, "ad_type": "SELL"}, "BINANCE|||Trusted-marchant|||181.29": {"available": 50000.0, "ad_type": "SELL"}, "BINANCE|||SafetyLife|||181.29": {"available": 28728.19, "ad_type": "SELL"}, "BINANCE|||quufaa-trader|||181.29": {"available": 49218.66, "ad_type": "SELL"}, "BINANCE|||asse-go-trade|||181.29": {"available": 49761.74, "ad_type": "SELL"}, "BINANCE|||Tinsaye_Z_Ethiopia|||181.29": {"available": 49448.07, "ad_type": "SELL"}, "BINANCE|||P2P trade only |||181.29": {"available": 47098.28, "ad_type": "SELL"}, "BINANCE|||Zdntrusted|||181.29": {"available": 95102.53, "ad_type": "SELL"}, "BINANCE|||crazy_change|||181.29": {"available": 49630.34, "ad_type": "SELL"}, "BINANCE|||Netbet|||181.29": {"available": 496261.34, "ad_type": "SELL"}, "BINANCE|||AK-Infinity |||181.29": {"available": 49426.28, "ad_type": "SELL"}, "BINANCE|||Regular  P2P|||181.29": {"available": 48151.94, "ad_type": "SELL"}, "BINANCE|||Bek-21|||181.29": {"available": 3500.0, "ad_type": "SELL"}, "BINANCE|||sayid12|||181.29": {"available": 49901.74, "ad_type": "SELL"}, "BINANCE|||tintaAm|||181.29": {"available": 1943.28, "ad_type": "SELL"}, "BINANCE|||Satoshi_Seekerr|||181.29": {"available": 49348.99, "ad_type": "SELL"}, "BINANCE|||Luke-Mr|||181.29": {"available": 47534.24, "ad_type": "SELL"}, "BINANCE|||User-f2522|||181.29": {"available": 50000.0, "ad_type": "SELL"}, "BINANCE|||Ahmedexchange1|||181.28": {"available": 4622.93, "ad_type": "SELL"}, "BINANCE|||Super_trader9|||181.28": {"available": 392133.09, "ad_type": "SELL"}, "BINANCE|||ETHIOPIA_DOLLAR|||181.28": {"available": 50000.0, "ad_type": "SELL"}, "BINANCE|||Mare_ab|||181.28": {"available": 1348.19, "ad_type": "SELL"}, "BINANCE|||MAYA-Bit|||181.28": {"available": 906210.9, "ad_type": "SELL"}, "BINANCE|||ETHIO USD|||181.28": {"available": 1500000.0, "ad_type": "SELL"}, "BINANCE|||AD1897-Crypto|||181.28": {"available": 42672.72, "ad_type": "SELL"}, "BINANCE|||ETHcryptoETH|||181.28": {"available": 49938.24, "ad_type": "SELL"}, "BINANCE|||Amana_Traders |||181.28": {"available": 150000.0, "ad_type": "SELL"}, "BINANCE|||The Flash ETB |||181.28": {"available": 151887.36, "ad_type": "SELL"}, "BINANCE|||All-possible|||181.28": {"available": 48760.15, "ad_type": "SELL"}, "BINANCE|||instant_payee|||181.28": {"available": 49114.74, "ad_type": "SELL"}, "BINANCE|||Top_Rate_Deals|||181.28": {"available": 46593.45, "ad_type": "SELL"}, "BINANCE|||Three million |||181.28": {"available": 50000.0, "ad_type": "SELL"}, "BINANCE|||Melata-_-|||181.28": {"available": 47620.96, "ad_type": "SELL"}, "BINANCE|||best p2p exchanger|||181.28": {"available": 48630.06, "ad_type": "SELL"}, "BINANCE|||Aslam72|||181.28": {"available": 49063.62, "ad_type": "SELL"}, "BINANCE|||Alazargasol|||181.28": {"available": 33907.88, "ad_type": "SELL"}, "BINANCE|||AlteWay-|||181.28": {"available": 3523.75, "ad_type": "SELL"}, "BINANCE|||junatrade|||181.28": {"available": 11.61, "ad_type": "SELL"}, "BINANCE|||Toyiba_c|||181.28": {"available": 400.0, "ad_type": "SELL"}, "BINANCE|||HalalTrader 02|||181.28": {"available": 402.92, "ad_type": "SELL"}, "BINANCE|||UrjiiTrade|||181.28": {"available": 49513.06, "ad_type": "SELL"}, "BINANCE|||CryptoFlow_12|||181.28": {"available": 49981.12, "ad_type": "SELL"}, "BINANCE|||IamH21|||181.28": {"available": 49863.46, "ad_type": "SELL"}, "BINANCE|||abfaTraders|||181.28": {"available": 185567.82, "ad_type": "SELL"}, "BINANCE|||FARUK-A|||181.28": {"available": 50000.0, "ad_type": "SELL"}, "BINANCE|||Gedilove|||181.28": {"available": 48022.09, "ad_type": "SELL"}, "BINANCE|||Kd__jr|||181.28": {"available": 10000.0, "ad_type": "SELL"}, "BINANCE|||HIN GAABBU _trader_A|||181.28": {"available": 47906.15, "ad_type": "SELL"}, "BINANCE|||ETHIO USD|||181.27": {"available": 1500000.0, "ad_type": "SELL"}, "BINANCE|||Aslam72|||181.27": {"available": 49637.17, "ad_type": "SELL"}, "BINANCE|||Pro Trader_1|||181.27": {"available": 14990.06, "ad_type": "SELL"}, "BINANCE|||OrbitCentral|||181.26": {"available": 20000.0, "ad_type": "SELL"}, "BINANCE|||ETHIO USD|||181.26": {"available": 1499875.34, "ad_type": "SELL"}, "BINANCE|||abenji|||181.26": {"available": 29990.05, "ad_type": "SELL"}, "BINANCE|||zuffy|||181.26": {"available": 30000.0, "ad_type": "SELL"}, "BINANCE|||abenu-Gg11|||181.25": {"available": 39937.86, "ad_type": "SELL"}, "BINANCE|||GO_UP_GO|||181.25": {"available": 1994437.56, "ad_type": "SELL"}, "BINANCE|||ADUNIX|||181.25": {"available": 48772.04, "ad_type": "SELL"}, "BINANCE|||SafeHold |||181.25": {"available": 49000.1, "ad_type": "SELL"}, "BINANCE|||Ambasel |||181.19": {"available": 194368.46, "ad_type": "SELL"}, "BINANCE|||Imran944a|||181.19": {"available": 119320.12, "ad_type": "SELL"}, "BINANCE|||Badhaasaatrade|||181.19": {"available": 30000.0, "ad_type": "SELL"}, "BINANCE|||SOTTmax|||181.19": {"available": 3134.04, "ad_type": "SELL"}, "BINANCE|||Omar_Bitcoin|||181.19": {"available": 980.43, "ad_type": "SELL"}, "BINANCE|||mire_02|||181.19": {"available": 31250.41, "ad_type": "SELL"}, "BINANCE|||nakuma|||181.19": {"available": 3740.23, "ad_type": "SELL"}, "BINANCE|||AB USD|||181.19": {"available": 49725.16, "ad_type": "SELL"}, "BINANCE|||Trusted-Exchange9|||181.19": {"available": 49388.65, "ad_type": "SELL"}, "BINANCE|||Marksolve|||181.19": {"available": 49676.74, "ad_type": "SELL"}, "BINANCE|||Dambalash |||181.19": {"available": 49980.0, "ad_type": "SELL"}, "BINANCE|||Baba inaya 17|||181.19": {"available": 50000.0, "ad_type": "SELL"}, "BINANCE|||AMIIN_TRADER|||181.18": {"available": 50000.0, "ad_type": "SELL"}, "BINANCE|||P2P-myTwinsAreComing|||181.18": {"available": 49868.97, "ad_type": "SELL"}, "BINANCE|||User-e5d6a|||181.18": {"available": 115.85, "ad_type": "SELL"}, "BINANCE|||Fufutrusted|||181.18": {"available": 8.91, "ad_type": "SELL"}, "BINANCE|||Digital-Diva|||181.18": {"available": 8835.49, "ad_type": "SELL"}, "BINANCE|||Philip-Jiao|||181.18": {"available": 1000.0, "ad_type": "SELL"}, "BINANCE|||tiktakh_cry|||181.18": {"available": 600.0, "ad_type": "SELL"}, "BINANCE|||HD-Hiyaw|||181.18": {"available": 45000.0, "ad_type": "SELL"}, "BINANCE|||iamdagi|||181.17": {"available": 50000.0, "ad_type": "SELL"}, "BINANCE|||Autonline|||181.17": {"available": 69685.28, "ad_type": "SELL"}, "BINANCE|||kalgold|||181.16": {"available": 2000.0, "ad_type": "SELL"}, "BINANCE|||Search-more|||181.16": {"available": 50000.0, "ad_type": "SELL"}, "BINANCE|||Shonna Molden n5i5|||181.16": {"available": 50000.0, "ad_type": "SELL"}, "BINANCE|||Aymi-Fi|||155.19": {"available": 10.0, "ad_type": "BUY"}, "BINANCE|||Tinsaye_Z_Ethiopia|||155.31": {"available": 100.0, "ad_type": "BUY"}, "BINANCE|||Eye-Trader|||155.36": {"available": 100.0, "ad_type": "BUY"}, "MEXC|||yeshi|||184.71": {"available": 374.0, "ad_type": "SELL"}, "MEXC|||Common-user-38606441|||184.7": {"available": 1404.9369, "ad_type": "SELL"}, "MEXC|||mudt|||184.7": {"available": 232.3993, "ad_type": "SELL"}, "MEXC|||ras@dudu|||184.65": {"available": 654.546, "ad_type": "SELL"}, "MEXC|||Common-user-38606441|||184.65": {"available": 800.3594, "ad_type": "SELL"}, "MEXC|||P2P-4848|||184.61": {"available": 1496.3019, "ad_type": "SELL"}, "MEXC|||keol|||184.6": {"available": 413.0793, "ad_type": "SELL"}, "MEXC|||keol|||184.59": {"available": 389.1626, "ad_type": "SELL"}, "MEXC|||arise95|||184.55": {"available": 1108.1098, "ad_type": "SELL"}, "MEXC|||Misra_1\u2705\ufe0f|||184.52": {"available": 239.5984, "ad_type": "SELL"}}