{"MEXC|||Common-user-38606441|||188.1": {"available": 2248.8106, "ad_type": "SELL"}, "MEXC|||Shalom-TraderET|||188.05": {"available": 4760.78, "ad_type": "SELL"}, "MEXC|||OJEMBA INTERNATIONAL|||188.04": {"available": 516.6241, "ad_type": "SELL"}, "MEXC|||Tiya fast|||188.04": {"available": 329.364, "ad_type": "SELL"}, "MEXC|||Luke_Mr|||188.02": {"available": 632.0859, "ad_type": "SELL"}, "MEXC|||NoorPay|||187.9": {"available": 1700.2814, "ad_type": "SELL"}, "MEXC|||y1000guaranee for trader|||187.88": {"available": 319.0, "ad_type": "SELL"}, "MEXC|||Common-user-47907339|||187.87": {"available": 53.25, "ad_type": "SELL"}, "MEXC|||Danff74|||187.81": {"available": 567.5492, "ad_type": "SELL"}, "MEXC|||hka trading|||187.61": {"available": 206.6294, "ad_type": "SELL"}, "MEXC|||Ab Trades|||187.6": {"available": 978.6751, "ad_type": "SELL"}, "MEXC|||P2P-4848|||187.56": {"available": 510.3299, "ad_type": "SELL"}, "MEXC|||Big Sami trader\ud83e\udd47|||187.51": {"available": 200.0, "ad_type": "SELL"}, "MEXC|||Waanofii -Crypto|||187.12": {"available": 143.3824, "ad_type": "SELL"}, "MEXC|||well come|||187.1": {"available": 155.1018, "ad_type": "SELL"}, "MEXC|||Honest75|||187.1": {"available": 95.13, "ad_type": "SELL"}, "MEXC|||\u011cg-11|||187.1": {"available": 45.5281, "ad_type": "SELL"}, "MEXC|||keol|||187.08": {"available": 453.8127, "ad_type": "SELL"}, "MEXC|||Medina1B|||187.0": {"available": 913.9545, "ad_type": "SELL"}, "MEXC|||Lemi fast worker|||187.0": {"available": 1610.0, "ad_type": "SELL"}, "MEXC|||MarGioM|||186.75": {"available": 579.5551, "ad_type": "SELL"}, "MEXC|||Trust Level|||186.5": {"available": 405.29, "ad_type": "SELL"}, "MEXC|||runnertra|||186.4": {"available": 186.8059, "ad_type": "SELL"}, "MEXC|||Mr.Dollaru|||186.39": {"available": 88.9622, "ad_type": "SELL"}, "MEXC|||Mr.Dollaru|||186.29": {"available": 257.4973, "ad_type": "SELL"}, "MEXC|||well come|||186.2": {"available": 247.0537, "ad_type": "SELL"}, "MEXC|||\ud83d\udc51fast\ud83d\udc51|||186.05": {"available": 2000.0, "ad_type": "SELL"}, "MEXC|||Mame_smart_trador|||186.0": {"available": 100.0, "ad_type": "SELL"}, "MEXC|||Gitsini|||186.0": {"available": 3745.8554, "ad_type": "SELL"}, "MEXC|||Nadi Young|||185.55": {"available": 500.0, "ad_type": "SELL"}, "MEXC|||All trade official|||185.5": {"available": 1860.8115, "ad_type": "SELL"}, "MEXC|||shiro-market|||185.1": {"available": 2835.1068, "ad_type": "SELL"}, "MEXC|||NAWRO  TRADE\u2705|||185.08": {"available": 67500.2391, "ad_type": "SELL"}, "MEXC|||Netbet|||185.0": {"available": 1386.8234, "ad_type": "SELL"}, "MEXC|||shiro-market|||184.7": {"available": 3784.8505, "ad_type": "SELL"}, "MEXC|||Waanofii -Crypto|||184.63": {"available": 345.7123, "ad_type": "SELL"}, "MEXC|||HT2424|||184.02": {"available": 3426.6288, "ad_type": "SELL"}, "MEXC|||user-H2a1\u2705|||184.0": {"available": 1147.8831, "ad_type": "SELL"}, "MEXC|||Gamine-365|||183.65": {"available": 12022.4709, "ad_type": "SELL"}}