{"MEXC|||Danival|||186.0": {"available": 42.0, "ad_type": "BUY"}, "MEXC|||HMIp2p|||189.5": {"available": 991.8, "ad_type": "BUY"}, "MEXC|||zionsi|||189.88": {"available": 141.962353, "ad_type": "BUY"}, "MEXC|||Ame tech|||189.9": {"available": 606.942, "ad_type": "BUY"}, "MEXC|||Lalo4as|||189.96": {"available": 511.4696, "ad_type": "BUY"}, "MEXC|||TrueTrader31|||190.19": {"available": 626.5336, "ad_type": "BUY"}, "MEXC|||Common-user-79436082|||190.2": {"available": 457.9701, "ad_type": "BUY"}, "MEXC|||AB live Ex|||190.7": {"available": 865.66, "ad_type": "BUY"}, "MEXC|||we grow 2gzr|||190.75": {"available": 5.583, "ad_type": "BUY"}, "MEXC|||Aviator_24/7|||190.8": {"available": 711.1778, "ad_type": "BUY"}, "MEXC|||love@|||190.8": {"available": 530.0072, "ad_type": "BUY"}, "MEXC|||meku|||191.0": {"available": 16.956, "ad_type": "BUY"}, "MEXC|||Tol2|||191.66": {"available": 230.5103, "ad_type": "BUY"}, "MEXC|||JR|||192.75": {"available": 282.5656, "ad_type": "BUY"}, "MEXC|||y1000guaranee for trader|||192.99": {"available": 525.4, "ad_type": "BUY"}, "MEXC|||zionsi|||193.4": {"available": 141.962353, "ad_type": "BUY"}, "MEXC|||Waanofii -Crypto|||193.7": {"available": 6.2901, "ad_type": "BUY"}, "MEXC|||NE33|||195.0": {"available": 984.138, "ad_type": "BUY"}, "MEXC|||Ben|||197.8": {"available": 55.0, "ad_type": "BUY"}}