{"MEXC|||Danival|||178.0": {"available": 44.0, "ad_type": "BUY"}, "MEXC|||Fast trader100%|||181.39": {"available": 73.3624, "ad_type": "BUY"}, "MEXC|||Welcome \ud83e\udd1d|||181.7": {"available": 531.9319, "ad_type": "BUY"}, "MEXC|||TrueTrader31|||181.78": {"available": 648.9732, "ad_type": "BUY"}, "MEXC|||well come|||182.0": {"available": 31.2088, "ad_type": "BUY"}, "MEXC|||Launch-pool Coin \ud83e\ude99|||182.0": {"available": 402.0793, "ad_type": "BUY"}, "MEXC|||Yonathan|||182.3": {"available": 110.575, "ad_type": "BUY"}, "MEXC|||well come|||182.4": {"available": 47.0, "ad_type": "BUY"}, "MEXC|||\u011cg-11|||182.45": {"available": 391.8556, "ad_type": "BUY"}, "MEXC|||NAWRO  TRADE\u2705|||182.48": {"available": 552.746, "ad_type": "BUY"}, "MEXC|||SwiftTrader2018|||182.49": {"available": 1226.0124, "ad_type": "BUY"}, "MEXC|||yeab3D|||182.5": {"available": 587.1259, "ad_type": "BUY"}, "MEXC|||Aviator_24/7|||182.5": {"available": 1189.6469, "ad_type": "BUY"}, "MEXC|||BigManET|||182.8": {"available": 1816.6526, "ad_type": "BUY"}, "MEXC|||tradebit|||182.95": {"available": 85.7616, "ad_type": "BUY"}, "MEXC|||keol|||183.0": {"available": 500.2228, "ad_type": "BUY"}, "MEXC|||Launch-pool Coin \ud83e\ude99|||183.0": {"available": 402.07934002, "ad_type": "BUY"}, "MEXC|||TrustPay ET|||183.3": {"available": 55.2232, "ad_type": "BUY"}, "MEXC|||yeab3D|||183.4": {"available": 587.1259, "ad_type": "BUY"}, "MEXC|||Aviator_24/7|||183.5": {"available": 1994.116198, "ad_type": "BUY"}, "MEXC|||Common-user-69088983|||183.78": {"available": 440.0, "ad_type": "BUY"}, "MEXC|||Abdii|||183.95": {"available": 378.1973, "ad_type": "BUY"}, "MEXC|||Bibo|||184.0": {"available": 794.351, "ad_type": "BUY"}, "MEXC|||NAWRO  TRADE\u2705|||184.17": {"available": 500.0, "ad_type": "BUY"}, "MEXC|||Yonathan|||184.9": {"available": 110.575, "ad_type": "BUY"}, "MEXC|||CNN News|||185.0": {"available": 659.885, "ad_type": "BUY"}, "MEXC|||shiro-market|||185.46": {"available": 1500.0, "ad_type": "BUY"}, "MEXC|||GTD_Alsen|||186.0": {"available": 1.02312998, "ad_type": "BUY"}, "MEXC|||meku|||186.33": {"available": 1054.0, "ad_type": "BUY"}, "MEXC|||SuleyXP|||187.5": {"available": 173.29, "ad_type": "BUY"}, "MEXC|||brookee|||187.9": {"available": 44.6314, "ad_type": "BUY"}, "MEXC|||Common-user-31299778|||188.0": {"available": 41.3204, "ad_type": "BUY"}, "MEXC|||Good_vibes|||188.0": {"available": 157.1567, "ad_type": "BUY"}, "MEXC|||24 gola 12|||188.5": {"available": 269.8706, "ad_type": "BUY"}, "MEXC|||ontime|||189.0": {"available": 2500.0, "ad_type": "BUY"}, "MEXC|||LMJ\ud83d\udfea\ud83d\udd37\ufe0f\ud83d\udfe9fast 3|||189.5": {"available": 1600.0, "ad_type": "BUY"}, "MEXC|||Yonathan|||189.9": {"available": 70.2106, "ad_type": "BUY"}, "MEXC|||Common-user-94651818|||189.95": {"available": 928.67, "ad_type": "BUY"}, "MEXC|||trustful|||189.99": {"available": 1127.7578, "ad_type": "BUY"}, "MEXC|||HalalTrader\u2705\ufe0f|||190.0": {"available": 18.5151, "ad_type": "BUY"}, "MEXC|||HalalTrader\u2705\ufe0f|||192.5": {"available": 18.5151, "ad_type": "BUY"}, "MEXC|||Mr.Dollaru|||195.5": {"available": 5.289408, "ad_type": "BUY"}, "MEXC|||Common-user-99603681|||198.0": {"available": 6.24, "ad_type": "BUY"}, "MEXC|||ET_Trade_Pro|||199.99": {"available": 0.5173, "ad_type": "BUY"}, "MEXC|||HalalTrader\u2705\ufe0f|||199.99": {"available": 18.5151, "ad_type": "BUY"}, "MEXC|||meku|||200.0": {"available": 1058.0, "ad_type": "BUY"}, "MEXC|||Wisemen|||220.0": {"available": 316.3553, "ad_type": "BUY"}, "MEXC|||Gitsini|||300.0": {"available": 1612.602, "ad_type": "BUY"}}