{"BINANCE|||Reliable for All|||181.3": {"available": 210.69, "ad_type": "SELL"}, "BINANCE|||Trusted_A|||181.3": {"available": 35461.94, "ad_type": "SELL"}, "BINANCE|||Eliana_Exc|||181.3": {"available": 37414.86, "ad_type": "SELL"}, "BINANCE|||BASHASHA BASHASHA|||181.3": {"available": 43521.08, "ad_type": "SELL"}, "BINANCE|||SabbanFastTrader|||181.3": {"available": 451776.49, "ad_type": "SELL"}, "BINANCE|||Aphteen47|||181.3": {"available": 45236.4, "ad_type": "SELL"}, "BINANCE|||P2P-725zs1Ilo|||181.3": {"available": 83538.1, "ad_type": "SELL"}, "BINANCE|||real huslter|||181.3": {"available": 974783.77, "ad_type": "SELL"}, "BINANCE|||Safe_Exchange_19|||181.3": {"available": 48859.68, "ad_type": "SELL"}, "BINANCE|||kemal abdu yasin |||181.3": {"available": 29050.5, "ad_type": "SELL"}, "BINANCE|||Gitsini|||181.3": {"available": 21937.67, "ad_type": "SELL"}, "BINANCE|||Harir Meri|||181.3": {"available": 43180.74, "ad_type": "SELL"}, "BINANCE|||Honest-Crypto1|||181.3": {"available": 45848.33, "ad_type": "SELL"}, "BINANCE|||HA--Exchange|||181.3": {"available": 48324.14, "ad_type": "SELL"}, "BINANCE|||The ultimate goal 1|||181.3": {"available": 48304.51, "ad_type": "SELL"}, "BINANCE|||Ella water|||181.3": {"available": 282.2, "ad_type": "SELL"}, "BINANCE|||Fast and safety payment|||181.29": {"available": 47836.11, "ad_type": "SELL"}, "BINANCE|||Diamond-ETB|||181.29": {"available": 45896.66, "ad_type": "SELL"}, "BINANCE|||BASHASHA BASHASHA77|||181.29": {"available": 49910.06, "ad_type": "SELL"}, "BINANCE|||Habesha p2p zone |||181.29": {"available": 50000.0, "ad_type": "SELL"}, "BINANCE|||the only one p2p |||181.29": {"available": 50000.0, "ad_type": "SELL"}, "BINANCE|||welcome back2677|||181.29": {"available": 49749.19, "ad_type": "SELL"}, "BINANCE|||no-one1|||181.29": {"available": 47023.96, "ad_type": "SELL"}, "BINANCE|||Common44|||181.29": {"available": 23655.89, "ad_type": "SELL"}, "BINANCE|||REAL-MONEY|||181.29": {"available": 998043.37, "ad_type": "SELL"}, "BINANCE|||abeembwbaz|||181.29": {"available": 49032.68, "ad_type": "SELL"}, "BINANCE|||Ti-Yam|||181.29": {"available": 47557.11, "ad_type": "SELL"}, "BINANCE|||All_trade_officail|||181.29": {"available": 47512.08, "ad_type": "SELL"}, "BINANCE|||B I S M I L L A A H I _ trader _99|||181.29": {"available": 36063.66, "ad_type": "SELL"}, "BINANCE|||Hayme_Man|||181.29": {"available": 4602.87, "ad_type": "SELL"}, "BINANCE|||Changeme21|||181.29": {"available": 495756.84, "ad_type": "SELL"}, "BINANCE|||FanToshi EXchange|||181.29": {"available": 887464.5, "ad_type": "SELL"}, "BINANCE|||AB-Mark|||181.29": {"available": 147260.16, "ad_type": "SELL"}, "BINANCE|||TawekalTrade|||181.29": {"available": 50000.0, "ad_type": "SELL"}, "BINANCE|||dodohavq|||181.29": {"available": 3520.13, "ad_type": "SELL"}, "BINANCE|||real_cryptoo|||181.29": {"available": 45320.15, "ad_type": "SELL"}, "BINANCE|||Trusted-marchant|||181.29": {"available": 50000.0, "ad_type": "SELL"}, "BINANCE|||SafetyLife|||181.29": {"available": 28537.34, "ad_type": "SELL"}, "BINANCE|||asse-go-trade|||181.29": {"available": 49733.77, "ad_type": "SELL"}, "BINANCE|||Tinsaye_Z_Ethiopia|||181.29": {"available": 49448.07, "ad_type": "SELL"}, "BINANCE|||P2P trade only |||181.29": {"available": 47098.28, "ad_type": "SELL"}, "BINANCE|||Zdntrusted|||181.29": {"available": 95060.59, "ad_type": "SELL"}, "BINANCE|||crazy_change|||181.29": {"available": 49607.4, "ad_type": "SELL"}, "BINANCE|||Netbet|||181.29": {"available": 496261.34, "ad_type": "SELL"}, "BINANCE|||AK-Infinity |||181.29": {"available": 49426.28, "ad_type": "SELL"}, "BINANCE|||Regular  P2P|||181.29": {"available": 48151.94, "ad_type": "SELL"}, "BINANCE|||Bek-21|||181.29": {"available": 3500.0, "ad_type": "SELL"}, "BINANCE|||sayid12|||181.29": {"available": 49901.74, "ad_type": "SELL"}, "BINANCE|||tintaAm|||181.29": {"available": 1928.37, "ad_type": "SELL"}, "BINANCE|||Satoshi_Seekerr|||181.29": {"available": 49348.99, "ad_type": "SELL"}, "BINANCE|||Luke-Mr|||181.29": {"available": 46043.36, "ad_type": "SELL"}, "BINANCE|||User-f2522|||181.29": {"available": 50000.0, "ad_type": "SELL"}, "BINANCE|||Ahmedexchange1|||181.28": {"available": 4622.93, "ad_type": "SELL"}, "BINANCE|||Super_trader9|||181.28": {"available": 391993.84, "ad_type": "SELL"}, "BINANCE|||ETHIOPIA_DOLLAR|||181.28": {"available": 50000.0, "ad_type": "SELL"}, "BINANCE|||MAYA-Bit|||181.28": {"available": 889910.93, "ad_type": "SELL"}, "BINANCE|||ETHIO USD|||181.28": {"available": 1500000.0, "ad_type": "SELL"}, "BINANCE|||AD1897-Crypto|||181.28": {"available": 42208.01, "ad_type": "SELL"}, "BINANCE|||ETHcryptoETH|||181.28": {"available": 49938.24, "ad_type": "SELL"}, "BINANCE|||Amana_Traders |||181.28": {"available": 150000.0, "ad_type": "SELL"}, "BINANCE|||The Flash ETB |||181.28": {"available": 148533.11, "ad_type": "SELL"}, "BINANCE|||All-possible|||181.28": {"available": 48760.15, "ad_type": "SELL"}, "BINANCE|||instant_payee|||181.28": {"available": 49114.74, "ad_type": "SELL"}, "BINANCE|||Top_Rate_Deals|||181.28": {"available": 46593.45, "ad_type": "SELL"}, "BINANCE|||Three million |||181.28": {"available": 50000.0, "ad_type": "SELL"}, "BINANCE|||Melata-_-|||181.28": {"available": 47574.05, "ad_type": "SELL"}, "BINANCE|||best p2p exchanger|||181.28": {"available": 48630.06, "ad_type": "SELL"}, "BINANCE|||Aslam72|||181.28": {"available": 49043.68, "ad_type": "SELL"}, "BINANCE|||Alazargasol|||181.28": {"available": 33745.43, "ad_type": "SELL"}, "BINANCE|||AlteWay-|||181.28": {"available": 3365.33, "ad_type": "SELL"}, "BINANCE|||Toyiba_c|||181.28": {"available": 400.0, "ad_type": "SELL"}, "BINANCE|||HalalTrader 02|||181.28": {"available": 381.23, "ad_type": "SELL"}, "BINANCE|||UrjiiTrade|||181.28": {"available": 49513.06, "ad_type": "SELL"}, "BINANCE|||CryptoFlow_12|||181.28": {"available": 49981.12, "ad_type": "SELL"}, "BINANCE|||IamH21|||181.28": {"available": 49677.98, "ad_type": "SELL"}, "BINANCE|||abfaTraders|||181.28": {"available": 185467.88, "ad_type": "SELL"}, "BINANCE|||FARUK-A|||181.28": {"available": 50000.0, "ad_type": "SELL"}, "BINANCE|||Gedilove|||181.28": {"available": 48022.09, "ad_type": "SELL"}, "BINANCE|||Kd__jr|||181.28": {"available": 10000.0, "ad_type": "SELL"}, "BINANCE|||Aymi-Fi|||155.19": {"available": 10.0, "ad_type": "BUY"}, "BINANCE|||Tinsaye_Z_Ethiopia|||155.31": {"available": 100.0, "ad_type": "BUY"}, "BINANCE|||Eye-Trader|||155.36": {"available": 100.0, "ad_type": "BUY"}, "MEXC|||Melak|||179.6": {"available": 517.4604, "ad_type": "BUY"}, "MEXC|||Tayeb7936|||184.4": {"available": 499.9901, "ad_type": "BUY"}, "MEXC|||Common-user-66896491|||184.5": {"available": 271.0029, "ad_type": "BUY"}, "MEXC|||AB-Mark|||184.65": {"available": 466.1653, "ad_type": "BUY"}, "MEXC|||TRADE HAB|||184.67": {"available": 920.5549, "ad_type": "BUY"}, "MEXC|||Fast trader100%|||184.79": {"available": 871.8765, "ad_type": "BUY"}, "MEXC|||SIIFOL|||184.8": {"available": 100.3339, "ad_type": "BUY"}, "MEXC|||Tayeb7936|||184.8": {"available": 500.5333, "ad_type": "BUY"}, "MEXC|||Autonline|||184.92": {"available": 539.2571, "ad_type": "BUY"}, "MEXC|||FanToshi Exchange \ud83d\udcb1|||184.94": {"available": 826.8752, "ad_type": "BUY"}, "MEXC|||shiro-market|||184.98": {"available": 660.1047, "ad_type": "BUY"}, "MEXC|||All trade official|||184.98": {"available": 44.3221, "ad_type": "BUY"}, "MEXC|||Trust Level|||184.99": {"available": 336.7566, "ad_type": "BUY"}, "MEXC|||Common-user-46881870|||185.2": {"available": 495.0591, "ad_type": "BUY"}, "MEXC|||sudina|||185.2": {"available": 974.369, "ad_type": "BUY"}, "MEXC|||OrbitCentral|||185.5": {"available": 102.0808, "ad_type": "BUY"}, "MEXC|||Investfarm|||185.5": {"available": 925.0, "ad_type": "BUY"}, "MEXC|||AK-Infinity|||185.6": {"available": 409.7669, "ad_type": "BUY"}, "MEXC|||Bahre99|||185.69": {"available": 162.4351, "ad_type": "BUY"}, "MEXC|||Joe+|||185.7": {"available": 223.0482, "ad_type": "BUY"}, "MEXC|||ET_Trusted|||185.7": {"available": 1169.7025, "ad_type": "BUY"}, "MEXC|||mastertrade|||185.75": {"available": 500.0, "ad_type": "BUY"}, "MEXC|||Hayme_Man|||185.79": {"available": 201.1658, "ad_type": "BUY"}, "MEXC|||Always_Me(3 Minute)|||185.8": {"available": 201.9276, "ad_type": "BUY"}, "MEXC|||Shalom-TraderET|||185.8": {"available": 97.85, "ad_type": "BUY"}, "MEXC|||MIX-trader|||185.8": {"available": 84.0612, "ad_type": "BUY"}, "MEXC|||Kokeb|||185.81": {"available": 182.7293, "ad_type": "BUY"}, "MEXC|||Shalom-TraderET|||185.85": {"available": 57.9509, "ad_type": "BUY"}, "MEXC|||Qimem|||185.88": {"available": 188.6164, "ad_type": "BUY"}, "MEXC|||well come|||185.9": {"available": 37.6366, "ad_type": "BUY"}, "MEXC|||\ud83d\udc8eFARUK\ud83d\udc8e|||185.92": {"available": 121.9895, "ad_type": "BUY"}, "MEXC|||HS2424|||185.93": {"available": 133.8231, "ad_type": "BUY"}, "MEXC|||Fast &amp; Relaible|||185.95": {"available": 13.4402, "ad_type": "BUY"}, "MEXC|||medina1B|||185.95": {"available": 186.7208, "ad_type": "BUY"}, "MEXC|||user-H2a1\u2705|||185.99": {"available": 337.1904, "ad_type": "BUY"}, "MEXC|||REAL MONEY|||186.0": {"available": 512.9013, "ad_type": "BUY"}, "MEXC|||maykankua|||186.2": {"available": 240.0082, "ad_type": "BUY"}, "MEXC|||Bibo|||186.25": {"available": 718.7823, "ad_type": "BUY"}, "MEXC|||Abdii|||186.37": {"available": 1012.3962, "ad_type": "BUY"}, "MEXC|||Luke_Mr|||186.38": {"available": 1602.0, "ad_type": "BUY"}}