{"MEXC|||Bahre99|||190.35": {"available": 625.68, "ad_type": "SELL"}, "MEXC|||Trusted/fast service provider|||189.0": {"available": 1580.5183, "ad_type": "SELL"}, "MEXC|||Abdii|||189.0": {"available": 194.6108, "ad_type": "SELL"}, "MEXC|||Anuu Tech Solution|||188.99": {"available": 514.3822, "ad_type": "SELL"}, "MEXC|||abdu1B|||188.95": {"available": 195.5076, "ad_type": "SELL"}, "MEXC|||Rasg-trusted\ud83e\udd47|||188.94": {"available": 509.8881, "ad_type": "SELL"}, "MEXC|||Luke_Mr|||188.85": {"available": 700.4665, "ad_type": "SELL"}, "MEXC|||Anuu Tech Solution|||188.83": {"available": 1209.4507, "ad_type": "SELL"}, "MEXC|||tenstar|||188.81": {"available": 511.8433, "ad_type": "SELL"}, "MEXC|||Ame tech|||188.8": {"available": 708.9282, "ad_type": "SELL"}, "MEXC|||Launch-pool Coin \ud83e\ude99|||188.74": {"available": 5681.9537, "ad_type": "SELL"}, "MEXC|||Luke_Mr|||188.72": {"available": 1590.9167, "ad_type": "SELL"}, "MEXC|||SwiftTrader2018|||188.66": {"available": 680.0, "ad_type": "SELL"}, "MEXC|||Abdii|||188.65": {"available": 364.248, "ad_type": "SELL"}, "MEXC|||Mr.Dollaru|||188.64": {"available": 407.4052, "ad_type": "SELL"}, "MEXC|||SwiftTrader2018|||188.62": {"available": 1398.2871, "ad_type": "SELL"}, "MEXC|||Mr.Dollaru|||188.61": {"available": 400.0, "ad_type": "SELL"}, "MEXC|||Common-Trader|||188.6": {"available": 2732.1292, "ad_type": "SELL"}, "MEXC|||Dlnaod|||188.57": {"available": 231.4685, "ad_type": "SELL"}, "MEXC|||Trust Level|||188.53": {"available": 400.4877, "ad_type": "SELL"}, "MEXC|||Anuu Tech Solution|||188.51": {"available": 257.6176, "ad_type": "SELL"}, "MEXC|||MarGioM|||188.5": {"available": 310.6906, "ad_type": "SELL"}, "MEXC|||AB was|||188.5": {"available": 590.1043, "ad_type": "SELL"}, "MEXC|||Tiya fast|||188.32": {"available": 969.6548, "ad_type": "SELL"}, "MEXC|||Np \ud83e\uddde\u200d\u2642\ufe0f|||188.3": {"available": 1684.8478, "ad_type": "SELL"}, "MEXC|||Seya_man|||188.3": {"available": 6052.7225, "ad_type": "SELL"}, "MEXC|||SIIFOL|||188.2": {"available": 110.1576, "ad_type": "SELL"}, "MEXC|||Seya_man|||188.15": {"available": 5876.867, "ad_type": "SELL"}, "MEXC|||runnertra|||188.1": {"available": 245.8356, "ad_type": "SELL"}, "MEXC|||Trust For All|||188.1": {"available": 790.7388, "ad_type": "SELL"}}