{"MEXC|||Mame_smart_trador|||186.0": {"available": 100.0, "ad_type": "SELL"}, "MEXC|||The Honest|||185.05": {"available": 990.5499, "ad_type": "SELL"}, "MEXC|||Never give up_A|||184.9": {"available": 1377.6179, "ad_type": "SELL"}, "MEXC|||trustful|||184.85": {"available": 136.7541, "ad_type": "SELL"}, "MEXC|||Big Sami trader\ud83e\udd47|||184.84": {"available": 268.2878, "ad_type": "SELL"}, "MEXC|||Dlnaod|||184.83": {"available": 65.5358, "ad_type": "SELL"}, "MEXC|||Shalom-TraderET|||184.76": {"available": 6245.259, "ad_type": "SELL"}, "MEXC|||\u221a Trust For All|||184.43": {"available": 253.9684, "ad_type": "SELL"}, "MEXC|||Girum|||184.41": {"available": 500.0, "ad_type": "SELL"}, "MEXC|||Luke_Mr|||184.32": {"available": 2826.6206, "ad_type": "SELL"}}