{"MEXC|||Alpha23-P2P|||184.25": {"available": 89.0236, "ad_type": "SELL"}, "MEXC|||LMJ\ud83d\udfea\ud83d\udd37\ufe0f\ud83d\udfe9fast 3|||184.21": {"available": 1629.0, "ad_type": "SELL"}, "MEXC|||we grow 2gzr|||184.13": {"available": 1500.0, "ad_type": "SELL"}, "MEXC|||OJEMBA INTERNATIONAL|||184.12": {"available": 690.0564, "ad_type": "SELL"}, "MEXC|||Always Trust|||184.05": {"available": 250.0, "ad_type": "SELL"}, "MEXC|||Honest man\ud83e\udd49|||184.03": {"available": 202.0, "ad_type": "SELL"}, "MEXC|||Always Trust|||184.02": {"available": 1260.0, "ad_type": "SELL"}, "MEXC|||TheSnipe|||184.0": {"available": 3200.0, "ad_type": "SELL"}, "MEXC|||\ud83d\udc9d&amp;\ud83e\udd1d|||183.3": {"available": 2000.0, "ad_type": "SELL"}, "MEXC|||Launch-pool Coin \ud83e\ude99|||183.08": {"available": 1255.0, "ad_type": "SELL"}, "MEXC|||hka trading|||182.86": {"available": 409.5778, "ad_type": "SELL"}, "MEXC|||Aviator_24/7|||182.51": {"available": 7124.8429, "ad_type": "SELL"}, "MEXC|||world \ud83c\udf0e pro|||182.51": {"available": 13120.5343, "ad_type": "SELL"}, "MEXC|||Navaye|||182.3": {"available": 473.15, "ad_type": "SELL"}, "MEXC|||\ud83d\udc9d&amp;\ud83e\udd1d|||182.2": {"available": 719.1201, "ad_type": "SELL"}, "MEXC|||world \ud83c\udf0e pro|||181.87": {"available": 20000.0, "ad_type": "SELL"}, "MEXC|||ontime|||181.81": {"available": 538.5669, "ad_type": "SELL"}, "MEXC|||Lalo4as|||181.01": {"available": 13940.1976, "ad_type": "SELL"}, "MEXC|||GTD_Alsen|||181.0": {"available": 80.0, "ad_type": "SELL"}, "MEXC|||Honest man\ud83e\udd49|||181.0": {"available": 170.0, "ad_type": "SELL"}}