{"MEXC|||Danival|||181.0": {"available": 48.0, "ad_type": "BUY"}, "MEXC|||Trust Level|||181.95": {"available": 70.3117, "ad_type": "BUY"}, "MEXC|||Ros61\ud83d\udc8e|||182.1": {"available": 145.7871, "ad_type": "BUY"}, "MEXC|||MIF.M|||182.48": {"available": 71.0523, "ad_type": "BUY"}, "MEXC|||Common-user-43981599|||182.5": {"available": 1315.9043, "ad_type": "BUY"}, "MEXC|||HT2424|||182.6": {"available": 1694.0, "ad_type": "BUY"}, "MEXC|||NAWRO  TRADE\u2705|||182.64": {"available": 1226.2375, "ad_type": "BUY"}, "MEXC|||AB live Ex|||182.65": {"available": 1563.2201, "ad_type": "BUY"}, "MEXC|||\u221a Trust For All|||182.8": {"available": 150.5399, "ad_type": "BUY"}, "MEXC|||Dlnaod|||182.89": {"available": 30.967, "ad_type": "BUY"}, "MEXC|||TheSnipe|||183.0": {"available": 1594.9395, "ad_type": "BUY"}, "MEXC|||Honest75|||183.0": {"available": 275.5658, "ad_type": "BUY"}, "MEXC|||ABU3|||183.5": {"available": 1425.134, "ad_type": "BUY"}, "MEXC|||Aviator_24/7|||183.5": {"available": 623.8896, "ad_type": "BUY"}, "MEXC|||Eseba001|||184.0": {"available": 827.0461, "ad_type": "BUY"}, "MEXC|||Hop New|||184.0": {"available": 117.3914, "ad_type": "BUY"}, "MEXC|||hka trading|||184.42": {"available": 208.4892, "ad_type": "BUY"}, "MEXC|||HT2424|||184.43": {"available": 1584.5941, "ad_type": "BUY"}, "MEXC|||love@|||185.0": {"available": 999.8658, "ad_type": "BUY"}, "MEXC|||safe wz me|||185.5": {"available": 653.6137, "ad_type": "BUY"}, "MEXC|||Yonathan|||185.5": {"available": 71.0328, "ad_type": "BUY"}, "MEXC|||Novatrade|||185.9": {"available": 699.8719, "ad_type": "BUY"}, "MEXC|||Hop New|||186.0": {"available": 100.0, "ad_type": "BUY"}, "MEXC|||Waanofii -Crypto|||187.0": {"available": 35.5992, "ad_type": "BUY"}, "MEXC|||QuantumLeap\ud83d\udc8e|||187.11": {"available": 52.4763, "ad_type": "BUY"}, "MEXC|||keol|||187.95": {"available": 567.9362, "ad_type": "BUY"}, "MEXC|||Hop New|||188.0": {"available": 36.1703, "ad_type": "BUY"}, "MEXC|||Yonathan|||198.89": {"available": 50.1288, "ad_type": "BUY"}, "MEXC|||Alex\u00a5\u00a9|||199.87": {"available": 145.8019, "ad_type": "BUY"}}