{"MEXC|||Danival|||183.0": {"available": 40.0, "ad_type": "BUY"}, "MEXC|||Fast trader100%|||184.29": {"available": 376.9034, "ad_type": "BUY"}, "MEXC|||Safe12-trade|||184.5": {"available": 95.4545, "ad_type": "BUY"}, "MEXC|||crypto Vault|||184.5": {"available": 5649.514, "ad_type": "BUY"}, "MEXC|||Welcome \ud83e\udd1d|||184.6": {"available": 412.7493, "ad_type": "BUY"}, "MEXC|||Barbus \ud83d\udd25fast|||184.6": {"available": 501.3159, "ad_type": "BUY"}, "MEXC|||Trust Level|||184.7": {"available": 368.0, "ad_type": "BUY"}, "MEXC|||GEBRU|||184.84": {"available": 140.0, "ad_type": "BUY"}, "MEXC|||bellon|||184.85": {"available": 739.6477, "ad_type": "BUY"}, "MEXC|||24 gola 12|||184.94": {"available": 170.8808, "ad_type": "BUY"}, "MEXC|||Trust\u00aetrader|||184.94": {"available": 905.0932, "ad_type": "BUY"}, "MEXC|||Honest man\ud83e\udd49|||184.95": {"available": 107.3468, "ad_type": "BUY"}, "MEXC|||Not_Common|||184.95": {"available": 600.0, "ad_type": "BUY"}, "MEXC|||runnertra|||184.95": {"available": 36.339, "ad_type": "BUY"}, "MEXC|||HT2424|||184.99": {"available": 600.1184, "ad_type": "BUY"}, "MEXC|||HMIp2p|||185.0": {"available": 629.1449, "ad_type": "BUY"}, "MEXC|||hka trading|||185.0": {"available": 112.7567, "ad_type": "BUY"}, "MEXC|||Always Trust|||185.19": {"available": 910.5521, "ad_type": "BUY"}, "MEXC|||Common-user-43981599|||185.2": {"available": 1250.0, "ad_type": "BUY"}, "MEXC|||FetanTrade|||185.2": {"available": 1000.0, "ad_type": "BUY"}, "MEXC|||AD97@Helis.|||185.25": {"available": 138.591, "ad_type": "BUY"}, "MEXC|||well come|||185.3": {"available": 50.0, "ad_type": "BUY"}, "MEXC|||BILLIONAIRE1|||185.4": {"available": 4677.6883, "ad_type": "BUY"}, "MEXC|||shiro-market|||185.48": {"available": 596.0793, "ad_type": "BUY"}, "MEXC|||Not_Common|||185.5": {"available": 600.0, "ad_type": "BUY"}, "MEXC|||ABU3|||185.5": {"available": 2665.2515, "ad_type": "BUY"}, "MEXC|||JR|||185.55": {"available": 140.4519, "ad_type": "BUY"}, "MEXC|||Novatrade|||185.59": {"available": 521.414, "ad_type": "BUY"}, "MEXC|||SwiftTrader2018|||185.59": {"available": 1650.0, "ad_type": "BUY"}, "MEXC|||Aviator_24/7|||185.69": {"available": 1593.9122, "ad_type": "BUY"}, "MEXC|||bellon|||185.85": {"available": 406.0, "ad_type": "BUY"}, "MEXC|||SONIC_TRD|||185.95": {"available": 568.0, "ad_type": "BUY"}, "MEXC|||we grow 2gzr|||185.99": {"available": 648.8114, "ad_type": "BUY"}, "MEXC|||NE33|||186.0": {"available": 1115.1907, "ad_type": "BUY"}, "MEXC|||REAL MONEY|||186.6": {"available": 2499.9909, "ad_type": "BUY"}, "MEXC|||CNN News|||187.0": {"available": 188.3357, "ad_type": "BUY"}, "MEXC|||Common-user-16091674|||187.15": {"available": 249.7142, "ad_type": "BUY"}, "MEXC|||Luke_Mr|||187.19": {"available": 1605.0, "ad_type": "BUY"}, "MEXC|||ontime|||187.2": {"available": 2200.0, "ad_type": "BUY"}}